{"000":{"r":"N135YX","t":"ULAC","f":"00","desc":"Waiex"},"019":{"r":"N135ZX","t":"PARA","f":"00","desc":""},"01C":{"r":"N1350","t":"PARA","f":"00","desc":""},"01D":{"r":"N1350A","t":"DC3","f":"00","desc":""},"01E":{"r":"N1350B","t":"L8","f":"00","desc":""},"020":{"r":"N1350D","t":"C170","f":"00","desc":""},"021":{"r":"N1350E","t":"CH7A","f":"00","desc":"1946 AERONCA 7AC"},"022":{"r":"N1350F","t":"C172","f":"00","desc":""},"025":{"r":"N1350J","t":"AC11","f":"00","desc":"1976 ROCKWELL INTERNATIONAL 112B"},"026":{"r":"N1350K","t":"L8","f":"00","desc":""},"02C":{"r":"N1350R","t":"AA1","f":"00","desc":"American Aviation AA-1B"},"02D":{"r":"N1350S","t":"CL35","f":"00","desc":"Bombardier Challenger 350"},"02F":{"r":"N1350U","t":"DHC1","f":"00","desc":""},"030":{"r":"N1350V","t":"C172","f":"00","desc":"Cessna R172K Hawk XP"},"033":{"r":"N1350Y","t":"C172","f":"00","desc":""},"035":{"r":"N13500","t":"C180","f":"00","desc":""},"039":{"r":"N13504","t":"C172","f":"00","desc":""},"03B":{"r":"N13506","t":"C172","f":"00","desc":""},"03C":{"r":"N13507","t":"C172","f":"00","desc":""},"03D":{"r":"N13508","t":"C172","f":"00","desc":""},"042":{"r":"N1351C","t":"C177","f":"00","desc":"CESSNA 177B"},"043":{"r":"N1351D","t":"C170","f":"00","desc":"1951 CESSNA 170A"},"044":{"r":"N1351E","t":"C172","f":"00","desc":"Cessna 172N Skyhawk"},"046":{"r":"N1351G","t":"C310","f":"00","desc":"1976 CESSNA 310R"},"04F":{"r":"N1351R","t":"BE36","f":"00","desc":"Beech Bonanza A36TC"},"050":{"r":"N1351S","t":"C182","f":"00","desc":"Cessna 182P Skylane"},"053":{"r":"N1351V","t":"J3","f":"00","desc":""},"054":{"r":"N1351W","t":"M20P","f":"00","desc":"1963 MOONEY M20C"},"056":{"r":"N1351Y","t":"C172","f":"00","desc":""},"057":{"r":"N1351Z","t":"BE55","f":"00","desc":""},"059":{"r":"N13511","t":"C177","f":"00","desc":"Cessna 177B Cardinal"},"05B":{"r":"N13513","t":"C172","f":"00","desc":""},"05D":{"r":"N13515","t":"C177","f":"00","desc":"Cessna 177B Cardinal"},"065":{"r":"N1352C","t":"PA18","f":"00","desc":"1953 PIPER PA-18A-135"},"067":{"r":"N1352E","t":"C172","f":"00","desc":"1978 CESSNA 172N"},"068":{"r":"N1352F","t":"C172","f":"00","desc":""},"06A":{"r":"N1352H","t":"AR15","f":"00","desc":""},"06B":{"r":"N1352J","t":"AC11","f":"00","desc":"1975 ROCKWELL INTERNATIONAL 112A"},"06F":{"r":"N1352N","t":"WCAT","f":"00","desc":""},"070":{"r":"N1352P","t":"PA23","f":"00","desc":""},"075":{"r":"N1352U","t":"C172","f":"00","desc":"1976 CESSNA 172M"},"076":{"r":"N1352V","t":"C172","f":"00","desc":""},"077":{"r":"N1352W","t":"SREY","f":"00","desc":"2014 PROGRESSIVE AERODYNE INC SEAREY LSA"},"079":{"r":"N1352Y","t":"C172","f":"00","desc":""},"07B":{"r":"N13520","t":"C172","f":"00","desc":"1973 CESSNA 172M"},"07C":{"r":"N13521","t":"C172","f":"00","desc":""},"07D":{"r":"N13522","t":"C172","f":"00","desc":""},"07E":{"r":"N13523","t":"C172","f":"00","desc":""},"07F":{"r":"N13524","t":"C172","f":"00","desc":"1973 CESSNA 172M"},"081":{"r":"N13526","t":"C177","f":"00","desc":"1976 CESSNA 177B"},"082":{"r":"N13527","t":"C172","f":"00","desc":""},"084":{"r":"N13529","t":"C172","f":"00","desc":""},"085":{"r":"N1353","t":"DRON","f":"00","desc":""},"087":{"r":"N1353B","t":"L8","f":"00","desc":""},"088":{"r":"N1353C","t":"C177","f":"00","desc":""},"08D":{"r":"N1353H","t":"AR15","f":"00","desc":""},"08E":{"r":"N1353J","t":"AC11","f":"00","desc":""},"090":{"r":"N1353L","t":"C337","f":"00","desc":""},"091":{"r":"N1353M","t":"ZZZZ","f":"00","desc":""},"092":{"r":"N1353N","t":"COUG","f":"00","desc":""},"093":{"r":"N1353P","t":"PA23","f":"00","desc":""},"095":{"r":"N1353R","t":"BE77","f":"00","desc":""},"096":{"r":"N1353S","t":"C182","f":"00","desc":"CESSNA 182P"},"098":{"r":"N1353U","t":"C172","f":"00","desc":""},"09C":{"r":"N1353Y","t":"P28A","f":"00","desc":""},"09D":{"r":"N1353Z","t":"GLID","f":"00","desc":"1981 APPLEBAY SAILPLANES ZUNI II"},"0A0":{"r":"N13532","t":"ZZZZ","f":"00","desc":""},"0A1":{"r":"N13533","t":"C172","f":"00","desc":""},"0A3":{"r":"N13535","t":"C172","f":"00","desc":"Cessna 172M Skyhawk"},"0A5":{"r":"N13537","t":"C172","f":"00","desc":"Cessna 172M Skyhawk"},"0A6":{"r":"N13538","t":"E145","f":"00","desc":"Embraer ERJ145LR"},"0A7":{"r":"N13539","t":"C172","f":"00","desc":""},"0AA":{"r":"N1354B","t":"L8","f":"00","desc":""},"0AC":{"r":"N1354D","t":"C170","f":"00","desc":""},"0AD":{"r":"N1354E","t":"C182","f":"00","desc":""},"0B0":{"r":"N1354H","t":"AR15","f":"00","desc":""},"0B1":{"r":"N1354J","t":"RV9","f":"00","desc":"2015 MURTAGH JOHN J VANS AIRCRAFT RV-9A"},"0B2":{"r":"N1354K","t":"L8","f":"00","desc":""},"0B7":{"r":"N1354Q","t":"C150","f":"00","desc":""},"0B8":{"r":"N1354R","t":"AA5","f":"00","desc":""},"0BA":{"r":"N1354T","t":"P28R","f":"00","desc":"Piper PA-28R 200 Cherokee Arrow II"},"0BB":{"r":"N1354U","t":"C172","f":"00","desc":"Cessna 172M Skyhawk"},"0BD":{"r":"N1354W","t":"","f":"00","desc":""},"0BE":{"r":"N1354X","t":"B47G","f":"00","desc":"1966 BELL 47G-4A"},"0C0":{"r":"N1354Z","t":"BE35","f":"00","desc":"1961 BEECH N35"},"0C1":{"r":"N13540","t":"C172","f":"00","desc":"Cessna 172M Skyhawk"},"0C2":{"r":"N13541","t":"C177","f":"00","desc":"1976 CESSNA 177B"},"0C4":{"r":"N13543","t":"C172","f":"00","desc":"Cessna 172M Skyhawk"},"0C5":{"r":"N13544","t":"C172","f":"00","desc":""},"0C9":{"r":"N13548","t":"C172","f":"00","desc":"1973 CESSNA 172M"},"0CA":{"r":"N13549","t":"C172","f":"00","desc":""},"0CB":{"r":"N1355","t":"GLID","f":"00","desc":""},"0CC":{"r":"N1355A","t":"PA18","f":"00","desc":""},"0CD":{"r":"N1355B","t":"C172","f":"00","desc":"Cessna 172S Skyhawk SP"},"0CE":{"r":"N1355C","t":"COL4","f":"00","desc":"2006 COLUMBIA AIRCRAFT MFG LC41-550FG"},"0CF":{"r":"N1355D","t":"C170","f":"00","desc":"1951 CESSNA 170A"},"0D0":{"r":"N1355E","t":"CH7A","f":"00","desc":""},"0D1":{"r":"N1355F","t":"C172","f":"00","desc":"Cessna 172N Skyhawk"},"0D4":{"r":"N1355J","t":"AC11","f":"00","desc":""},"0DB":{"r":"N1355R","t":"AA5","f":"00","desc":""},"0DC":{"r":"N1355S","t":"C182","f":"00","desc":""},"0DD":{"r":"N1355T","t":"PA32","f":"00","desc":"1972 PIPER PA-32-300"},"0E0":{"r":"N1355W","t":"M20P","f":"00","desc":""},"0E3":{"r":"N1355Z","t":"BE35","f":"00","desc":""},"0E4":{"r":"N13550","t":"E145","f":"00","desc":"Embraer ERJ145LR"},"0E5":{"r":"N13551","t":"C172","f":"00","desc":"1973 CESSNA 172M"},"0E6":{"r":"N13552","t":"C172","f":"00","desc":"1973 CESSNA 172M"},"0E7":{"r":"N13553","t":"E145","f":"00","desc":"2002 EMBRAER EMB-145LR"},"0E8":{"r":"N13554","t":"ULAC","f":"00","desc":""},"0E9":{"r":"N13555","t":"C172","f":"00","desc":"1973 CESSNA 172M"},"0EA":{"r":"N13556","t":"ULAC","f":"00","desc":""},"0EC":{"r":"N13558","t":"C172","f":"00","desc":""},"0ED":{"r":"N13559","t":"C172","f":"00","desc":"Cessna 172M Skyhawk"},"0F0":{"r":"N1356B","t":"BIPL","f":"00","desc":""},"0F2":{"r":"N1356D","t":"C170","f":"00","desc":""},"0F4":{"r":"N1356F","t":"C172","f":"00","desc":"1979 CESSNA 172N"},"0F8":{"r":"N1356K","t":"L8","f":"00","desc":""},"0FB":{"r":"N1356N","t":"ST75","f":"00","desc":""},"0FD":{"r":"N1356Q","t":"PTS1","f":"00","desc":""},"0FF":{"r":"N1356S","t":"C182","f":"00","desc":"1976 CESSNA 182P"},"101":{"r":"N1356U","t":"C172","f":"00","desc":"1976 CESSNA 172M"},"103":{"r":"N1356W","t":"SA10","f":"00","desc":""},"105":{"r":"N1356Y","t":"SA10","f":"00","desc":""},"107":{"r":"N13560","t":"C177","f":"00","desc":"Cessna 177B Cardinal"},"108":{"r":"N13561","t":"WACO","f":"00","desc":""},"109":{"r":"N13562","t":"WACO","f":"00","desc":""},"10A":{"r":"N13563","t":"WACO","f":"00","desc":""},"10B":{"r":"N13564","t":"C177","f":"00","desc":"Cessna 177B Cardinal"},"10C":{"r":"N13565","t":"C177","f":"00","desc":"1976 CESSNA 177B"},"10D":{"r":"N13566","t":"E145","f":"00","desc":"2002 EMBRAER EMB-145LR"},"10E":{"r":"N13567","t":"WACO","f":"00","desc":""},"112":{"r":"N1357A","t":"PA18","f":"00","desc":"1951 PIPER PA-18"},"119":{"r":"N1357H","t":"AR15","f":"00","desc":"AERONCA 15AC"},"11E":{"r":"N1357N","t":"ST75","f":"00","desc":""},"11F":{"r":"N1357P","t":"GLID","f":"00","desc":"1976 LAISTER SAILPLANE INC. LP-15"},"120":{"r":"N1357Q","t":"C150","f":"00","desc":"1971 CESSNA 150L"},"122":{"r":"N1357S","t":"C182","f":"00","desc":"1976 CESSNA 182P"},"124":{"r":"N1357U","t":"C172","f":"00","desc":"1976 CESSNA 172M"},"128":{"r":"N1357Y","t":"C172","f":"00","desc":""},"12A":{"r":"N13570","t":"WACO","f":"00","desc":""},"12B":{"r":"N13571","t":"","f":"00","desc":""},"12C":{"r":"N13572","t":"WACO","f":"00","desc":""},"12D":{"r":"N13573","t":"C172","f":"00","desc":"Cessna 172M Skyhawk"},"12E":{"r":"N13574","t":"C195","f":"00","desc":""},"130":{"r":"N13576","t":"ZZZZ","f":"00","desc":""},"133":{"r":"N13579","t":"GYRO","f":"00","desc":""},"135":{"r":"N1358A","t":"PA18","f":"00","desc":""},"137":{"r":"N1358C","t":"SR22","f":"00","desc":""},"139":{"r":"N1358E","t":"CH7A","f":"00","desc":""},"13E":{"r":"N1358K","t":"L8","f":"00","desc":""},"140":{"r":"N1358M","t":"ST75","f":"00","desc":""},"143":{"r":"N1358Q","t":"C150","f":"00","desc":"1971 CESSNA 150L"},"146":{"r":"N1358T","t":"P28A","f":"00","desc":""},"147":{"r":"N1358U","t":"C172","f":"00","desc":""},"149":{"r":"N1358W","t":"M20P","f":"00","desc":""},"150":{"r":"N13583","t":"ULAC","f":"00","desc":""},"153":{"r":"N13586","t":"C172","f":"00","desc":""},"154":{"r":"N13587","t":"C172","f":"00","desc":"1973 CESSNA 172M"},"158":{"r":"N1359A","t":"BE33","f":"00","desc":""},"159":{"r":"N1359B","t":"C182","f":"00","desc":"2007 CESSNA 182T"},"15A":{"r":"N1359C","t":"C177","f":"00","desc":""},"15B":{"r":"N1359D","t":"C170","f":"00","desc":""},"15E":{"r":"N1359G","t":"C310","f":"00","desc":"1976 CESSNA 310R"},"162":{"r":"N1359L","t":"RV7","f":"00","desc":"Vans RV-7 A"},"163":{"r":"N1359M","t":"C182","f":"00","desc":"Cessna 182P Skylane"},"164":{"r":"N1359N","t":"ST75","f":"00","desc":""},"166":{"r":"N1359Q","t":"RV3","f":"00","desc":""},"167":{"r":"N1359R","t":"AA5","f":"00","desc":""},"169":{"r":"N1359T","t":"P28A","f":"00","desc":""},"16A":{"r":"N1359U","t":"C172","f":"00","desc":"Cessna 172M Skyhawk"},"16B":{"r":"N1359V","t":"FOX","f":"00","desc":""},"16C":{"r":"N1359W","t":"M20P","f":"00","desc":""},"170":{"r":"N13590","t":"C172","f":"00","desc":""},"172":{"r":"N13592","t":"C172","f":"00","desc":"Cessna 172M Skyhawk"},"173":{"r":"N13593","t":"C172","f":"00","desc":"Cessna 172M Skyhawk"},"174":{"r":"N13594","t":"C172","f":"00","desc":"1973 CESSNA 172M"},"177":{"r":"N13597","t":"C177","f":"00","desc":"1976 CESSNA 177B"},"17B":{"r":"N136A","t":"PA11","f":"00","desc":"2015 CUBCRAFTERS INC CC11-160"},"17C":{"r":"N136AA","t":"BE36","f":"00","desc":"1985 BEECH A36"},"17E":{"r":"N136AC","t":"BL8","f":"00","desc":""},"181":{"r":"N136AF","t":"BE36","f":"00","desc":"1981 BEECH A36"},"185":{"r":"N136AK","t":"SR22","f":"00","desc":"Cirrus SR22"},"187":{"r":"N136AM","t":"BE36","f":"00","desc":"1991 BEECH A36"},"188":{"r":"N136AN","t":"A321","f":"00","desc":"2015 AIRBUS A321-231"},"18F":{"r":"N136AV","t":"P28A","f":"00","desc":"Piper PA-28 181 Archer II"},"194":{"r":"N136B","t":"BE36","f":"00","desc":"Beech Bonanza A36"},"195":{"r":"N136BA","t":"BE35","f":"00","desc":""},"196":{"r":"N136BB","t":"GLID","f":"00","desc":""},"197":{"r":"N136BC","t":"ZZZZ","f":"00","desc":"2013 ROBERT E BOUNDS BOUNDS BEARCOUPE"},"198":{"r":"N136BD","t":"RV8","f":"00","desc":""},"199":{"r":"N136BE","t":"B36T","f":"00","desc":"Beech B36TC Bonanza"},"19A":{"r":"N136BF","t":"B36T","f":"00","desc":""},"19C":{"r":"N136BH","t":"H60","f":"00","desc":"1992 SIKORSKY S70A-27"},"1A4":{"r":"N136BR","t":"PA27","f":"00","desc":"1979 PIPER PA-23-250"},"1AE":{"r":"N136CA","t":"CVLP","f":"00","desc":"Convair 440 -40"},"1AF":{"r":"N136CB","t":"BALL","f":"00","desc":""},"1B0":{"r":"N136CC","t":"PA18","f":"00","desc":""},"1B1":{"r":"N136CD","t":"BE36","f":"00","desc":"Beech Bonanza A36"},"1B5":{"r":"N136CH","t":"RV4","f":"00","desc":""},"1BB":{"r":"N136CP","t":"M7","f":"00","desc":""},"1BE":{"r":"N136CS","t":"LNC4","f":"00","desc":""},"1BF":{"r":"N136CT","t":"FDCT","f":"00","desc":""},"1C2":{"r":"N136CW","t":"BE36","f":"00","desc":"1984 BEECH A36"},"1C3":{"r":"N136CX","t":"DG80","f":"00","desc":""},"1C6":{"r":"N136D","t":"AC11","f":"00","desc":""},"1C7":{"r":"N136DA","t":"DV20","f":"00","desc":"Diamond Aircraft Katana DA20-C1"},"1C9":{"r":"N136DC","t":"GLAS","f":"00","desc":""},"1CA":{"r":"N136DD","t":"BE36","f":"00","desc":"Beech Bonanza A36TC"},"1CB":{"r":"N136DE","t":"SRAI","f":"00","desc":""},"1CE":{"r":"N136DH","t":"LJ35","f":"00","desc":"Gates Learjet 36 A"},"1CF":{"r":"N136DJ","t":"RV7","f":"00","desc":""},"1D0":{"r":"N136DK","t":"RV6","f":"00","desc":""},"1D2":{"r":"N136DM","t":"B407","f":"00","desc":"2012 BELL HELICOPTER TEXTRON CANADA 407"},"1D7":{"r":"N136DS","t":"DA40","f":"00","desc":"Diamond Aircraft Diamond Star DA40"},"1D8":{"r":"N136DT","t":"HDJT","f":"00","desc":"Honda Aircraft Company Honda Jet HA-420"},"1D9":{"r":"N136DU","t":"EC35","f":"00","desc":"2007 EUROCOPTER DEUTSCHLAND GMBH EC 135 T2+"},"1DB":{"r":"N136DW","t":"PA44","f":"00","desc":"2003 PIPER PA-44-180"},"1DF":{"r":"N136E","t":"EA50","f":"00","desc":""},"1E0":{"r":"N136EA","t":"EA50","f":"00","desc":"Eclipse EA500"},"1E7":{"r":"N136EH","t":"BE36","f":"00","desc":"1979 BEECH A36"},"1E8":{"r":"N136EJ","t":"PA38","f":"00","desc":""},"1EB":{"r":"N136EM","t":"L39","f":"00","desc":"1984 AERO VODOCHODY L39C"},"1F3":{"r":"N136EV","t":"CRJ9","f":"00","desc":"2009 BOMBARDIER INC CL-600-2D24"},"1F8":{"r":"N136F","t":"RV6","f":"00","desc":""},"1FB":{"r":"N136FC","t":"P28A","f":"00","desc":""},"203":{"r":"N136FL","t":"ULAC","f":"00","desc":""},"20E":{"r":"N136FX","t":"GLF5","f":"00","desc":""},"213":{"r":"N136GB","t":"BE35","f":"00","desc":"Beech Bonanza V35"},"219":{"r":"N136GH","t":"BE36","f":"00","desc":"Beech Bonanza A36"},"221":{"r":"N136GR","t":"BE36","f":"00","desc":"1983 BEECH A36"},"222":{"r":"N136GS","t":"RV10","f":"00","desc":""},"22A":{"r":"N136H","t":"PA15","f":"00","desc":""},"22C":{"r":"N136HB","t":"BE36","f":"00","desc":"2013 HAWKER BEECHCRAFT CORP G36"},"238":{"r":"N136HP","t":"BE36","f":"00","desc":"1984 BEECH B36T"},"239":{"r":"N136HQ","t":"E170","f":"00","desc":"2008 EMBRAER-EMPRESA BRASILEIRA DE ERJ 170-200 LR"},"23B":{"r":"N136HS","t":"M7","f":"00","desc":""},"243":{"r":"N136J","t":"C205","f":"00","desc":"1962 CESSNA 210-5(205)"},"244":{"r":"N136JA","t":"RV6","f":"00","desc":""},"245":{"r":"N136JB","t":"ULAC","f":"00","desc":""},"247":{"r":"N136JD","t":"C560","f":"00","desc":"1995 CESSNA 560"},"24C":{"r":"N136JJ","t":"BE18","f":"00","desc":"1957 BEECH E18S"},"24E":{"r":"N136JL","t":"BE36","f":"00","desc":"2009 HAWKER BEECHCRAFT CORP G36"},"24F":{"r":"N136JM","t":"PA22","f":"00","desc":""},"251":{"r":"N136JP","t":"LJ35","f":"00","desc":"GATES LEARJET CORP. 35A"},"253":{"r":"N136JR","t":"GLID","f":"00","desc":""},"254":{"r":"N136JS","t":"B06","f":"00","desc":""},"258":{"r":"N136JW","t":"BE36","f":"00","desc":"Beech Bonanza A36"},"259":{"r":"N136JX","t":"LJ60","f":"00","desc":""},"25C":{"r":"N136K","t":"BE36","f":"00","desc":"2000 RAYTHEON AIRCRAFT COMPANY A36"},"25D":{"r":"N136KA","t":"SR22","f":"00","desc":"Cirrus Design SR22T"},"25F":{"r":"N136KC","t":"BE36","f":"00","desc":"1978 BEECH A36"},"262":{"r":"N136KF","t":"B350","f":"00","desc":"Textron Aviation King Air B350"},"273":{"r":"N136KY","t":"EC35","f":"00","desc":"EUROCOPTER DEUTSCHLAND GMBH EC 135 P2"},"276":{"r":"N136LA","t":"R44","f":"00","desc":""},"277":{"r":"N136LB","t":"GYRO","f":"00","desc":""},"278":{"r":"N136LC","t":"VELO","f":"00","desc":"173RG"},"281":{"r":"N136LM","t":"C172","f":"00","desc":"1975 CESSNA 172M"},"28F":{"r":"N136MA","t":"DV20","f":"00","desc":"2004 DIAMOND AIRCRAFT IND INC DA20-C1"},"290":{"r":"N136MB","t":"BE10","f":"00","desc":"1978 BEECH B100"},"294":{"r":"N136MF","t":"EC35","f":"00","desc":"2005 EUROCOPTER DEUTSCHLAND GMBH EC135T2"},"295":{"r":"N136MG","t":"AT5T","f":"00","desc":""},"296":{"r":"N136MH","t":"EC35","f":"01","desc":"2000 EUROCOPTER DEUTSCHLAND GMBH EC135T1"},"29A":{"r":"N136MM","t":"RV6","f":"00","desc":""},"29C":{"r":"N136MP","t":"M20P","f":"00","desc":""},"29F":{"r":"N136MS","t":"PA18","f":"00","desc":""},"2A0":{"r":"N136MT","t":"ALIG","f":"00","desc":"Arion Lightning"},"2A2":{"r":"N136MV","t":"FA5X","f":"00","desc":"2001 DASSAULT AVIATION MYSTERE-FALCON 50"},"2A7":{"r":"N136N","t":"DA40","f":"00","desc":"2012 DIAMOND AIRCRAFT IND INC DA 40"},"2C1":{"r":"N136PA","t":"BE9L","f":"00","desc":"1975 BEECH C90"},"2C3":{"r":"N136PC","t":"BE36","f":"00","desc":"1984 BEECH A36"},"2C8":{"r":"N136PH","t":"EC30","f":"00","desc":"2004 EUROCOPTER EC 130 B4"},"2C9":{"r":"N136PJ","t":"BE36","f":"00","desc":"Beech Bonanza A36"},"2D1":{"r":"N136PS","t":"PTS2","f":"00","desc":""},"2D5":{"r":"N136PW","t":"GLID","f":"00","desc":""},"2D9":{"r":"N136Q","t":"C182","f":"00","desc":""},"2F4":{"r":"N136RB","t":"ULAC","f":"00","desc":"1999 OFFIELD RONNIE KOLB FIRESTAR"},"2F5":{"r":"N136RC","t":"RV6","f":"00","desc":""},"2F8":{"r":"N136RF","t":"BE36","f":"00","desc":"1995 BEECH A36"},"2FC":{"r":"N136RK","t":"BE36","f":"00","desc":"Raytheon Aircraft Bonanza G36"},"2FD":{"r":"N136RL","t":"BE36","f":"00","desc":"Beech Bonanza A36"},"302":{"r":"N136RR","t":"BT36","f":"00","desc":""},"306":{"r":"N136RV","t":"RV6","f":"00","desc":""},"307":{"r":"N136RW","t":"SR20","f":"00","desc":"2010 CIRRUS DESIGN CORP SR20"},"30C":{"r":"N136SA","t":"AA5","f":"00","desc":"American-General AG-5B Tiger"},"30E":{"r":"N136SC","t":"PARA","f":"00","desc":""},"310":{"r":"N136SE","t":"ULAC","f":"00","desc":""},"313":{"r":"N136SH","t":"BE36","f":"00","desc":"1994 BEECH A36"},"315":{"r":"N136SK","t":"BE36","f":"00","desc":"Raytheon Aircraft Bonanza G36"},"317":{"r":"N136SM","t":"E300","f":"00","desc":"1998 EXTRA FLUGZEUGBAU GMBH EA 300\/L"},"319":{"r":"N136SP","t":"S108","f":"00","desc":""},"31B":{"r":"N136SR","t":"SREY","f":"00","desc":""},"31D":{"r":"N136ST","t":"C182","f":"00","desc":"Cessna 182Q Skylane"},"322":{"r":"N136SY","t":"E170","f":"00","desc":"Embraer ERJ170-200LR"},"324":{"r":"N136T","t":"M20T","f":"00","desc":""},"326":{"r":"N136TB","t":"BE36","f":"00","desc":"Hawker Beechcraft A36 Bonanza"},"327":{"r":"N136TC","t":"BE36","f":"00","desc":"1979 BEECH A36TC"},"328":{"r":"N136TD","t":"PULS","f":"00","desc":""},"329":{"r":"N136TE","t":"EA50","f":"00","desc":"2007 ECLIPSE AVIATION CORP EA500"},"332":{"r":"N136TP","t":"BE36","f":"00","desc":"Beech\u00ef\u00bf\u00bdA36 Bonanza"},"334":{"r":"N136TR","t":"RV6","f":"00","desc":""},"336":{"r":"N136TT","t":"COL4","f":"00","desc":"2010 CESSNA AIRCRAFT CO LC41-550FG"},"338":{"r":"N136TV","t":"C182","f":"00","desc":""},"339":{"r":"N136TW","t":"B06","f":"00","desc":""},"34B":{"r":"N136UP","t":"A306","f":"00","desc":"2001 AIRBUS INDUSTRIE A300F4-622R"},"34F":{"r":"N136UT","t":"EC35","f":"00","desc":"2009 EUROCOPTER DEUTSCHLAND GMBH EC 135 P2+"},"364":{"r":"N136VP","t":"P28A","f":"00","desc":""},"366":{"r":"N136VR","t":"ZZZZ","f":"00","desc":""},"369":{"r":"N136VU","t":"C172","f":"00","desc":"2003 CESSNA 172R"},"36F":{"r":"N136W","t":"RBEL","f":"00","desc":""},"375":{"r":"N136WF","t":"RBEL","f":"00","desc":""},"399":{"r":"N136XS","t":"RF10","f":"00","desc":""},"3A1":{"r":"N136Y","t":"PA24","f":"00","desc":""},"3AF":{"r":"N136YP","t":"GLID","f":"00","desc":""},"3B7":{"r":"N136YX","t":"WAIX","f":"00","desc":"2010 CASTRILLO IVAN F WAIEX"},"3BD":{"r":"N136ZC","t":"GLF6","f":"00","desc":"2002 GULFSTREAM AEROSPACE G-V"},"3D5":{"r":"N1360B","t":"L8","f":"00","desc":""},"3D6":{"r":"N1360C","t":"SR22","f":"00","desc":"Cirrus Design SR22"},"3D8":{"r":"N1360E","t":"C172","f":"00","desc":""},"3DC":{"r":"N1360J","t":"AC11","f":"00","desc":""},"3DD":{"r":"N1360K","t":"L8","f":"00","desc":""},"3DE":{"r":"N1360L","t":"C337","f":"00","desc":"1978 CESSNA 337H"},"3E3":{"r":"N1360R","t":"AA1","f":"00","desc":""},"3E5":{"r":"N1360T","t":"P28R","f":"00","desc":"1972 PIPER PA-28R-200"},"3E8":{"r":"N1360W","t":"M20P","f":"00","desc":"Mooney M.20C Mark 21"},"3ED":{"r":"N13601","t":"C172","f":"00","desc":""},"3EE":{"r":"N13602","t":"C172","f":"00","desc":""},"3F0":{"r":"N13604","t":"C172","f":"00","desc":""},"3F1":{"r":"N13605","t":"C172","f":"00","desc":""},"3F7":{"r":"N1361A","t":"PA18","f":"00","desc":"Piper PA-18 150 Super Cub"},"3F9":{"r":"N1361C","t":"C177","f":"00","desc":"1977 CESSNA 177B"},"3FA":{"r":"N1361D","t":"C170","f":"00","desc":""},"3FB":{"r":"XB-JPN","t":"AT3P","f":"00","desc":"Air Tractor AT-301"},"3FC":{"r":"N1361F","t":"C172","f":"00","desc":""},"3FD":{"r":"N1361G","t":"C402","f":"00","desc":"1980 CESSNA 402C"},"3FE":{"r":"N1361H","t":"AR15","f":"00","desc":""},"3FF":{"r":"N1361J","t":"AC11","f":"00","desc":""},"400":{"r":"N1361K","t":"L8","f":"00","desc":""},"402":{"r":"N1361M","t":"C172","f":"00","desc":"2005 CESSNA 172S"},"403":{"r":"N1361N","t":"ST75","f":"00","desc":""},"405":{"r":"N1361Q","t":"C310","f":"00","desc":""},"406":{"r":"N1361R","t":"AA5","f":"00","desc":"1975 GRUMMAN AMERICAN AVN. CORP. AA-5"},"407":{"r":"N1361S","t":"COZY","f":"00","desc":""},"40A":{"r":"N1361V","t":"C206","f":"00","desc":"1974 CESSNA U206F"},"40D":{"r":"N1361Y","t":"C172","f":"00","desc":""},"40E":{"r":"N1361Z","t":"BE35","f":"00","desc":"1961 BEECH N35"},"410":{"r":"N13611","t":"C172","f":"00","desc":""},"411":{"r":"N13612","t":"C177","f":"00","desc":"1976 CESSNA 177B"},"417":{"r":"N13618","t":"C172","f":"00","desc":"Cessna 172M Skyhawk"},"418":{"r":"N13619","t":"C172","f":"00","desc":""},"419":{"r":"N1362","t":"DRON","f":"00","desc":""},"41A":{"r":"N1362A","t":"BE35","f":"00","desc":""},"41B":{"r":"N1362B","t":"AVID","f":"00","desc":"1994 BOYD BRUCE AVID FLYER"},"41C":{"r":"N1362C","t":"C340","f":"00","desc":""},"41D":{"r":"N1362D","t":"C170","f":"00","desc":""},"41F":{"r":"N1362F","t":"C185","f":"00","desc":"1975 CESSNA A185F"},"420":{"r":"N1362G","t":"C310","f":"00","desc":"Cessna 310R"},"421":{"r":"N1362H","t":"P28A","f":"00","desc":"PIPER PA-28-161"},"422":{"r":"N1362J","t":"AC11","f":"00","desc":"1975 ROCKWELL INTERNATIONAL 112A"},"429":{"r":"N1362R","t":"SONX","f":"00","desc":""},"42B":{"r":"N1362T","t":"COL4","f":"00","desc":"2007 COLUMBIA AIRCRAFT MFG LC41-550FG"},"42F":{"r":"N1362X","t":"B47G","f":"00","desc":"47"},"430":{"r":"N1362Y","t":"C172","f":"00","desc":""},"433":{"r":"N13621","t":"C177","f":"00","desc":"1976 CESSNA 177B"},"435":{"r":"N13623","t":"C172","f":"00","desc":""},"437":{"r":"N13625","t":"ZZZZ","f":"00","desc":""},"43B":{"r":"N13629","t":"CH7A","f":"00","desc":""},"43C":{"r":"N1363","t":"DRON","f":"00","desc":""},"43D":{"r":"N1363A","t":"PA18","f":"00","desc":""},"441":{"r":"N1363E","t":"CH7A","f":"00","desc":""},"444":{"r":"N1363H","t":"AR15","f":"00","desc":""},"44B":{"r":"N1363Q","t":"C150","f":"00","desc":"Cessna 150L"},"44D":{"r":"N1363S","t":"C182","f":"00","desc":"Cessna 182P Skylane"},"450":{"r":"N1363V","t":"ST75","f":"00","desc":""},"451":{"r":"N1363W","t":"UH1","f":"00","desc":""},"453":{"r":"N1363Y","t":"C172","f":"00","desc":""},"454":{"r":"N1363Z","t":"BE35","f":"00","desc":""},"457":{"r":"N13632","t":"C172","f":"00","desc":"Cessna 172M Skyhawk"},"458":{"r":"N13633","t":"C172","f":"00","desc":""},"45A":{"r":"N13635","t":"C172","f":"00","desc":"1974 CESSNA 172M"},"45C":{"r":"N13637","t":"SACE","f":"00","desc":""},"45E":{"r":"N13639","t":"C172","f":"00","desc":""},"45F":{"r":"N1364","t":"GYRO","f":"00","desc":""},"460":{"r":"N1364A","t":"PA18","f":"00","desc":""},"462":{"r":"N1364C","t":"PA18","f":"00","desc":""},"463":{"r":"N1364D","t":"C170","f":"00","desc":""},"465":{"r":"N1364F","t":"C172","f":"00","desc":"1966 CESSNA 172G"},"467":{"r":"N1364H","t":"AR15","f":"00","desc":""},"468":{"r":"N1364J","t":"T6","f":"00","desc":""},"469":{"r":"N1364K","t":"L8","f":"00","desc":""},"46C":{"r":"N1364N","t":"COL4","f":"00","desc":"2006 COLUMBIA AIRCRAFT MFG LC41-550FG"},"46D":{"r":"N1364P","t":"PA18","f":"00","desc":"1965 PIPER PA-18-150"},"471":{"r":"N1364T","t":"P28A","f":"00","desc":""},"472":{"r":"N1364U","t":"C172","f":"00","desc":""},"477":{"r":"N1364Z","t":"BE35","f":"00","desc":""},"47A":{"r":"N13642","t":"AT5T","f":"00","desc":""},"47C":{"r":"N13644","t":"C172","f":"00","desc":"1974 CESSNA 172M"},"47D":{"r":"N13645","t":"C172","f":"00","desc":"1974 CESSNA 172M"},"47E":{"r":"N13646","t":"C172","f":"00","desc":"1974 CESSNA 172M"},"47F":{"r":"N13647","t":"C177","f":"00","desc":"Cessna 177B Cardinal"},"482":{"r":"N1365","t":"C177","f":"00","desc":""},"483":{"r":"N1365A","t":"PA18","f":"00","desc":""},"484":{"r":"N1365B","t":"C180","f":"00","desc":"1971 CESSNA 180H"},"485":{"r":"N1365C","t":"PA18","f":"00","desc":"1953 PIPER PA-18-135"},"488":{"r":"N1365F","t":"C172","f":"00","desc":""},"48A":{"r":"N1365H","t":"AR15","f":"00","desc":""},"48B":{"r":"N1365J","t":"PA11","f":"00","desc":""},"48C":{"r":"N1365K","t":"L8","f":"00","desc":"1946 LUSCOMBE 8A"},"48D":{"r":"N1365L","t":"C337","f":"00","desc":""},"48E":{"r":"N1365M","t":"C182","f":"00","desc":"1975 CESSNA 182P"},"48F":{"r":"N1365N","t":"","f":"00","desc":""},"494":{"r":"N1365T","t":"P28A","f":"00","desc":""},"495":{"r":"N1365U","t":"C172","f":"00","desc":""},"49A":{"r":"N1365Z","t":"BE55","f":"00","desc":""},"4A1":{"r":"N13656","t":"C177","f":"00","desc":""},"4A3":{"r":"N13658","t":"C172","f":"00","desc":""},"4A4":{"r":"N13659","t":"C172","f":"00","desc":""},"4A5":{"r":"N1366","t":"DHC1","f":"00","desc":""},"4A6":{"r":"N1366A","t":"PA18","f":"00","desc":""},"4A8":{"r":"N1366C","t":"PA18","f":"00","desc":""},"4A9":{"r":"N1366D","t":"C170","f":"00","desc":""},"4AB":{"r":"N1366F","t":"C172","f":"00","desc":""},"4AC":{"r":"N1366G","t":"SONX","f":"00","desc":""},"4B3":{"r":"N1366P","t":"PA23","f":"00","desc":""},"4B5":{"r":"N1366R","t":"AA5","f":"00","desc":""},"4B8":{"r":"N1366U","t":"C172","f":"00","desc":"1976 CESSNA 172M"},"4BC":{"r":"N1366Y","t":"C172","f":"00","desc":""},"4BD":{"r":"N1366Z","t":"BE55","f":"00","desc":""},"4BE":{"r":"N13660","t":"C172","f":"00","desc":"Cessna 172M Skyhawk"},"4C0":{"r":"N13662","t":"C172","f":"00","desc":""},"4C5":{"r":"N13667","t":"C177","f":"00","desc":""},"4C6":{"r":"N13668","t":"C172","f":"00","desc":"Cessna 172M Skyhawk"},"4C7":{"r":"N13669","t":"C177","f":"00","desc":"1976 CESSNA 177B"},"4C8":{"r":"N1367","t":"BLKS","f":"00","desc":""},"4C9":{"r":"N1367A","t":"PA18","f":"00","desc":"1951 PIPER PA-18-125"},"4CA":{"r":"N1367B","t":"EAGL","f":"00","desc":""},"4CB":{"r":"N1367C","t":"PA18","f":"00","desc":""},"4CE":{"r":"N1367F","t":"C172","f":"00","desc":""},"4D6":{"r":"N1367P","t":"PA23","f":"00","desc":""},"4DA":{"r":"N1367T","t":"P28R","f":"00","desc":""},"4DC":{"r":"N1367V","t":"ST75","f":"00","desc":""},"4DD":{"r":"N1367W","t":"M20P","f":"00","desc":"Mooney M.20C Mark 21"},"4DF":{"r":"N1367Y","t":"SCOR","f":"00","desc":""},"4E3":{"r":"N13672","t":"C172","f":"00","desc":"Cessna 172M Skyhawk"},"4E4":{"r":"N13673","t":"C172","f":"00","desc":""},"4E5":{"r":"N13674","t":"C172","f":"00","desc":"Cessna 172M Skyhawk"},"4E6":{"r":"N13675","t":"C172","f":"00","desc":""},"4E8":{"r":"N13677","t":"ULAC","f":"00","desc":""},"4EC":{"r":"N1368A","t":"PA18","f":"00","desc":""},"4ED":{"r":"N1368B","t":"T18","f":"00","desc":""},"4EE":{"r":"N1368C","t":"SR22","f":"00","desc":"Cirrus Design SR22"},"4F1":{"r":"N1368F","t":"ZZZZ","f":"00","desc":""},"4F3":{"r":"N1368H","t":"AR15","f":"00","desc":""},"4F7":{"r":"N1368M","t":"GL5T","f":"00","desc":"2013 BOMBARDIER INC BD-700-1A11"},"4F9":{"r":"N1368P","t":"G2CA","f":"00","desc":""},"4FC":{"r":"N1368S","t":"C182","f":"00","desc":""},"4FE":{"r":"N1368U","t":"C172","f":"00","desc":""},"501":{"r":"N1368X","t":"B06","f":"00","desc":""},"502":{"r":"N1368Y","t":"BD5","f":"00","desc":""},"504":{"r":"N13680","t":"C172","f":"00","desc":""},"505":{"r":"N13681","t":"C177","f":"00","desc":"1976 CESSNA 177B"},"506":{"r":"N13682","t":"C172","f":"00","desc":""},"507":{"r":"N13683","t":"C172","f":"00","desc":""},"508":{"r":"N13684","t":"C172","f":"00","desc":""},"509":{"r":"N13685","t":"C172","f":"00","desc":""},"50A":{"r":"N13686","t":"C172","f":"00","desc":"1974 CESSNA 172M"},"50E":{"r":"N1369","t":"T18","f":"00","desc":""},"510":{"r":"N1369B","t":"CH7B","f":"00","desc":"1972 BELLANCA 7GCBC"},"512":{"r":"N1369D","t":"C170","f":"00","desc":""},"513":{"r":"N1369E","t":"CH7A","f":"00","desc":""},"514":{"r":"N1369F","t":"C172","f":"00","desc":""},"517":{"r":"N1369J","t":"AC11","f":"00","desc":""},"51D":{"r":"N1369Q","t":"C172","f":"00","desc":"2005 CESSNA 172S"},"51E":{"r":"N1369R","t":"AA5","f":"00","desc":""},"520":{"r":"N1369T","t":"PA34","f":"00","desc":"1972 PIPER PA-34-200"},"525":{"r":"N1369Y","t":"C172","f":"00","desc":""},"526":{"r":"N1369Z","t":"SRAI","f":"00","desc":"2000 ZAHN GARY SONERAI"},"527":{"r":"N13690","t":"C177","f":"00","desc":"1976 CESSNA 177B"},"528":{"r":"N13691","t":"CAMP","f":"00","desc":""},"529":{"r":"N13692","t":"C172","f":"00","desc":""},"52A":{"r":"N13693","t":"C172","f":"00","desc":"1974 CESSNA 172M"},"52D":{"r":"N13696","t":"C172","f":"00","desc":""},"52F":{"r":"N13698","t":"C172","f":"00","desc":""},"531":{"r":"N137","t":"C310","f":"00","desc":""},"533":{"r":"N137AA","t":"A321","f":"00","desc":"2015 AIRBUS A321-231"},"535":{"r":"N137AC","t":"BL8","f":"00","desc":""},"539":{"r":"N137AG","t":"B06","f":"00","desc":""},"53C":{"r":"N137AK","t":"MCOU","f":"00","desc":""},"53D":{"r":"N137AL","t":"C172","f":"00","desc":"Cessna 172N Skyhawk"},"53E":{"r":"N137AM","t":"EC35","f":"00","desc":"Eurocopter EC135-P2"},"540":{"r":"N137AP","t":"ULAC","f":"00","desc":""},"543":{"r":"N137AS","t":"BE76","f":"00","desc":""},"544":{"r":"N137AT","t":"P28A","f":"00","desc":"Piper PA-28 161 Warrior II"},"54A":{"r":"N137AZ","t":"RV12","f":"00","desc":""},"54B":{"r":"N137B","t":"ZZZZ","f":"00","desc":"Aeropro A220"},"54C":{"r":"N137BA","t":"BE99","f":"00","desc":""},"54D":{"r":"N137BB","t":"GLEX","f":"00","desc":"2005 BOMBARDIER INC BD-700-1A10"},"54E":{"r":"N137BC","t":"P28A","f":"00","desc":"Piper PA-28 181 Archer III"},"551":{"r":"N137BF","t":"BE36","f":"00","desc":"Raytheon Aircraft Bonanza G36"},"552":{"r":"N137BG","t":"C25B","f":"00","desc":"2005 CESSNA 525B"},"553":{"r":"N137BH","t":"H60","f":"00","desc":"S-70"},"55B":{"r":"N137BR","t":"LJ40","f":"00","desc":"2007 LEARJET INC 45"},"560":{"r":"N137BW","t":"C56X","f":"00","desc":"Cessna Citation Excel"},"564":{"r":"N137C","t":"HUSK","f":"00","desc":"1999 AVIAT AIRCRAFT INC A-1A"},"566":{"r":"N137CB","t":"C172","f":"00","desc":""},"567":{"r":"N137CC","t":"P28R","f":"00","desc":""},"568":{"r":"N137CD","t":"C425","f":"00","desc":"CESSNA 425"},"56B":{"r":"N137CG","t":"B733","f":"00","desc":""},"575":{"r":"N137CS","t":"PA31","f":"00","desc":""},"576":{"r":"N137CT","t":"FDCT","f":"00","desc":""},"579":{"r":"YV2951","t":"PAY1","f":"00","desc":"Piper PA-31T1 Cheyenne I"},"57D":{"r":"N137D","t":"C310","f":"00","desc":"1981 CESSNA 310R"},"57F":{"r":"N137DB","t":"CL60","f":"00","desc":""},"580":{"r":"N137DC","t":"C340","f":"00","desc":"1979 CESSNA 340A"},"585":{"r":"N137DH","t":"RV7","f":"00","desc":"2006 HOOD FRANK DALE RV-7"},"586":{"r":"N137DJ","t":"ULAC","f":"00","desc":""},"589":{"r":"N137DM","t":"M20P","f":"00","desc":"1979 MOONEY M20J"},"58D":{"r":"N137DR","t":"GLF4","f":"00","desc":""},"58E":{"r":"N137DS","t":"RV7","f":"00","desc":""},"592":{"r":"N137DW","t":"SC01","f":"00","desc":"PETER KILLCOMMONS SPEED CANARD-3"},"596":{"r":"N137E","t":"PARA","f":"00","desc":""},"599":{"r":"N137EC","t":"CH7A","f":"00","desc":"7EC"},"59A":{"r":"N137ED","t":"GLID","f":"00","desc":"1999 SCHLEICHER ASW-27"},"5A2":{"r":"N137EM","t":"L39","f":"00","desc":"Aero Vodochody L-39 C"},"5A4":{"r":"N137EP","t":"T18","f":"00","desc":""},"5A6":{"r":"N137ER","t":"TAMP","f":"00","desc":""},"5A7":{"r":"N137ES","t":"C150","f":"00","desc":""},"5AA":{"r":"N137EV","t":"CRJ9","f":"00","desc":"2009 BOMBARDIER INC CL-600-2D24"},"5AF":{"r":"N137F","t":"BE55","f":"00","desc":""},"5B0":{"r":"N137FA","t":"FA50","f":"00","desc":"1983 DASSAULT-BREGUET FALCON 50"},"5B2":{"r":"N137FC","t":"P28A","f":"00","desc":""},"5B4":{"r":"N137FE","t":"B763","f":"00","desc":"Boeing 767 3S2F"},"5BA":{"r":"N137FL","t":"B350","f":"00","desc":""},"5BF":{"r":"N137FR","t":"C172","f":"00","desc":"Cessna 172Q Cutlass"},"5C0":{"r":"N137FS","t":"C172","f":"00","desc":"Cessna 172M Skyhawk"},"5C8":{"r":"N137G","t":"RV6","f":"00","desc":""},"5CA":{"r":"N137GB","t":"COL3","f":"00","desc":"Columbia LC42-550FG"},"5D1":{"r":"N137GJ","t":"GLF2","f":"00","desc":"1968 GRUMMAN G-1159"},"5DD":{"r":"N137GW","t":"EC30","f":"00","desc":"2013 EUROCOPTER EC 130 T2"},"5EE":{"r":"N137HN","t":"EC30","f":"00","desc":"2012 EUROCOPTER EC 130 B4"},"5EF":{"r":"N137HP","t":"GA8","f":"01","desc":"GippsAero GA8 TC-320"},"5F0":{"r":"N137HQ","t":"E170","f":"00","desc":"2008 EMBRAER-EMPRESA BRASILEIRA DE ERJ 170-200 LR"},"5F2":{"r":"N137HS","t":"B06","f":"00","desc":"1977 BELL 206B"},"5FC":{"r":"N137JB","t":"AA1","f":"00","desc":"1978 GRUMMAN AMERICAN AVN. CORP. AA-1C"},"5FD":{"r":"N137JC","t":"C560","f":"00","desc":"1991 CESSNA 560"},"5FE":{"r":"N137JD","t":"WT9","f":"00","desc":""},"602":{"r":"N137JH","t":"PA31","f":"00","desc":"Piper PA-31 350 Navajo Chieftain"},"605":{"r":"N137JL","t":"TTWO","f":"00","desc":""},"606":{"r":"N137JM","t":"RV9","f":"00","desc":"2006 MARTIN JAMES RV-9A"},"608":{"r":"N137JP","t":"BE58","f":"00","desc":"1982 BEECH 58"},"609":{"r":"N137JQ","t":"C25C","f":"00","desc":"2013 CESSNA 525C"},"60A":{"r":"N137JR","t":"DHC6","f":"00","desc":"De Havilland Canada DHC-6 Twin Otter 200"},"60B":{"r":"N137JS","t":"H269","f":"00","desc":""},"60F":{"r":"N137JW","t":"BL8","f":"00","desc":"2011 AMERICAN CHAMPION AIRCRAFT 8GCBC"},"613":{"r":"N137K","t":"GLST","f":"00","desc":""},"616":{"r":"N137KC","t":"DA40","f":"00","desc":"2011 DIAMOND AIRCRAFT IND INC DA 40"},"618":{"r":"N137KE","t":"","f":"00","desc":""},"61E":{"r":"N137KL","t":"BALL","f":"00","desc":"2008 CAMERON BALLOONS US C-80"},"61F":{"r":"N137KM","t":"P46T","f":"00","desc":"2001 PIPER AIRCRAFT INC PA46-500TP"},"625":{"r":"N137KT","t":"LNC2","f":"00","desc":"1997 HECKMAN HARRY H LANCAIR 235"},"62C":{"r":"N137L","t":"ULAC","f":"00","desc":""},"62E":{"r":"N137LB","t":"JAB4","f":"00","desc":""},"62F":{"r":"N137LC","t":"RV9","f":"00","desc":""},"631":{"r":"N137LE","t":"DRON","f":"00","desc":""},"634":{"r":"N137LH","t":"R44","f":"00","desc":"2006 ROBINSON HELICOPTER COMPANY R44 II"},"638":{"r":"N137LM","t":"ECHO","f":"00","desc":""},"63D":{"r":"N137LS","t":"T28","f":"00","desc":""},"63F":{"r":"N137LU","t":"SR22","f":"00","desc":"Cirrus Design SR22"},"645":{"r":"N137M","t":"B06","f":"00","desc":""},"646":{"r":"N137MA","t":"C172","f":"00","desc":"1997 CESSNA 172R"},"647":{"r":"N137MB","t":"BALL","f":"00","desc":"2007 STUMPF PAUL S BOLLEA-54"},"648":{"r":"N137MC","t":"C337","f":"00","desc":""},"64A":{"r":"N137ME","t":"C172","f":"00","desc":"Cessna 172S Skyhawk SP"},"64B":{"r":"N137MF","t":"NAVI","f":"00","desc":""},"64D":{"r":"N137MH","t":"EC35","f":"00","desc":"2002 EUROCOPTER DEUTSCHLAND GMBH EC135P1"},"651":{"r":"N137MM","t":"B06","f":"00","desc":""},"652":{"r":"N137MN","t":"DRON","f":"00","desc":""},"655":{"r":"N137MR","t":"RV8","f":"00","desc":"2005 ROSE MARK G VANS RV-8A"},"656":{"r":"N137MS","t":"B06","f":"00","desc":""},"657":{"r":"N137MT","t":"R44","f":"00","desc":"Robinson R44 Raven"},"65A":{"r":"N137MW","t":"BN2P","f":"00","desc":"1970 BRITTEN-NORMAN BN-2A"},"65E":{"r":"N137N","t":"AEST","f":"00","desc":""},"65F":{"r":"N137NA","t":"T28","f":"00","desc":""},"665":{"r":"N137NG","t":"DRON","f":"00","desc":""},"677":{"r":"N137P","t":"C206","f":"01","desc":"2008 CESSNA 206H"},"679":{"r":"N137PB","t":"DC3","f":"00","desc":""},"67A":{"r":"N137PC","t":"CH7B","f":"00","desc":""},"67B":{"r":"N137PD","t":"B407","f":"01","desc":"2000 BELL 407"},"67C":{"r":"N137PE","t":"SR22","f":"00","desc":"2001 CIRRUS DESIGN CORP SR22"},"67F":{"r":"N137PH","t":"EC30","f":"00","desc":"Eurocopter EC130-B4"},"685":{"r":"N137PP","t":"ULAC","f":"00","desc":""},"689":{"r":"N137PT","t":"M20T","f":"00","desc":"2008 MOONEY AIRPLANE CO INC M20TN"},"6A9":{"r":"N137R","t":"EN28","f":"00","desc":""},"6AB":{"r":"N137RB","t":"GLID","f":"00","desc":""},"6AD":{"r":"N137RD","t":"DRON","f":"00","desc":""},"6B1":{"r":"N137RH","t":"LJ60","f":"00","desc":"1994 LEARJET INC 60"},"6B2":{"r":"N137RJ","t":"C172","f":"00","desc":"1999 CESSNA 172S"},"6B5":{"r":"N137RM","t":"BE20","f":"00","desc":""},"6BD":{"r":"N137RV","t":"RV7","f":"00","desc":""},"6C2":{"r":"N137S","t":"RV6","f":"00","desc":""},"6C5":{"r":"N137SC","t":"CRUZ","f":"00","desc":""},"6C6":{"r":"N137SD","t":"P32R","f":"00","desc":"1995 PIPER PA-32-301"},"6C9":{"r":"N137SG","t":"PC12","f":"00","desc":"Pilatus PC-XII 45"},"6CD":{"r":"N137SL","t":"P180","f":"00","desc":"Piaggio P-180 Avanti"},"6D2":{"r":"N137SR","t":"SR22","f":"00","desc":"Cirrus Design SR22"},"6D3":{"r":"N137SS","t":"GLID","f":"00","desc":""},"6D4":{"r":"N137ST","t":"W11","f":"00","desc":""},"6D7":{"r":"N137SW","t":"CRER","f":"00","desc":""},"6DB":{"r":"N137T","t":"PA18","f":"00","desc":""},"6DF":{"r":"N137TD","t":"R44","f":"00","desc":"2013 ROBINSON HELICOPTER R44"},"6E5":{"r":"N137TK","t":"BE20","f":"00","desc":"RAYTHEON AIRCRAFT COMPANY B200"},"6EC":{"r":"N137TS","t":"T206","f":"00","desc":""},"6ED":{"r":"N137TT","t":"PTS1","f":"00","desc":"Amateur Built Pitts Special S-1S"},"6F0":{"r":"N137TW","t":"BE35","f":"00","desc":"Beech Bonanza V35B"},"6F1":{"r":"N137TX","t":"RV4","f":"00","desc":""},"6F4":{"r":"N137U","t":"L37","f":"00","desc":""},"6FC":{"r":"N137UH","t":"DRON","f":"00","desc":""},"702":{"r":"N137UP","t":"A306","f":"00","desc":"2001 AIRBUS INDUSTRIE A300F4-622R"},"705":{"r":"N137US","t":"UH1","f":"00","desc":""},"71B":{"r":"N137VP","t":"P28A","f":"00","desc":""},"71D":{"r":"N137VR","t":"ZZZZ","f":"00","desc":""},"71F":{"r":"N137VT","t":"S10S","f":"00","desc":"2013 STEMME AG STEMME S 10-VT"},"720":{"r":"N137VU","t":"C172","f":"00","desc":"2003 CESSNA 172R"},"726":{"r":"N137W","t":"GP3","f":"00","desc":"2001 WUORINEN WILLIAM J OSPREY 2"},"728":{"r":"N137WB","t":"G200","f":"00","desc":"2006 ISRAEL AIRCRAFT INDUSTRIES GULFSTREAM 200"},"737":{"r":"N137WS","t":"GLF4","f":"00","desc":"1997 GULFSTREAM AEROSPACE G-IV"},"73F":{"r":"N137X","t":"LNP4","f":"00","desc":""},"749":{"r":"N137XK","t":"XA42","f":"00","desc":""},"750":{"r":"N137XS","t":"RF10","f":"00","desc":""},"758":{"r":"N137Y","t":"AA1","f":"00","desc":""},"77D":{"r":"N137ZM","t":"GL5T","f":"00","desc":"2008 BOMBARDIER INC BD-700-1A11"},"787":{"r":"N137ZX","t":"PARA","f":"00","desc":""},"797":{"r":"N1370N","t":"SA6","f":"00","desc":""},"799":{"r":"N1370Q","t":"C185","f":"00","desc":""},"79A":{"r":"N1370R","t":"PARA","f":"00","desc":""},"79B":{"r":"N1370S","t":"C182","f":"00","desc":"Cessna 182P Skylane"},"79D":{"r":"N1370U","t":"C172","f":"00","desc":""},"79E":{"r":"N1370V","t":"ST75","f":"00","desc":"1943 BOEING E75"},"7A3":{"r":"N13700","t":"ZZZZ","f":"00","desc":""},"7A4":{"r":"N13701","t":"C172","f":"00","desc":"Cessna 172M Skyhawk"},"7A6":{"r":"N13703","t":"C172","f":"00","desc":"1974 CESSNA 172M"},"7A8":{"r":"N13705","t":"","f":"00","desc":""},"7A9":{"r":"N13706","t":"KR2","f":"00","desc":""},"7AC":{"r":"N13709","t":"C206","f":"00","desc":"2007 CESSNA T206H"},"7AE":{"r":"N1371A","t":"CAMP","f":"00","desc":""},"7B0":{"r":"N1371C","t":"PA18","f":"00","desc":""},"7B1":{"r":"N1371D","t":"C170","f":"00","desc":""},"7B3":{"r":"N1371F","t":"C172","f":"00","desc":""},"7B4":{"r":"N1371G","t":"C310","f":"00","desc":"Cessna 310R"},"7B6":{"r":"N1371J","t":"AC11","f":"00","desc":""},"7B7":{"r":"N1371K","t":"","f":"00","desc":""},"7B9":{"r":"N1371M","t":"C177","f":"00","desc":""},"7BF":{"r":"N1371T","t":"P28A","f":"00","desc":""},"7C0":{"r":"N1371U","t":"C172","f":"00","desc":""},"7C1":{"r":"N1371V","t":"ST75","f":"00","desc":""},"7C3":{"r":"N1371X","t":"B47G","f":"00","desc":"1966 BELL 47G-3B-1"},"7C4":{"r":"N1371Y","t":"C172","f":"00","desc":""},"7C6":{"r":"N13710","t":"C177","f":"00","desc":""},"7C7":{"r":"N13711","t":"DC2","f":"00","desc":"DC-2"},"7CB":{"r":"N13715","t":"C172","f":"00","desc":"Cessna 172M Skyhawk"},"7CC":{"r":"N13716","t":"B737","f":"00","desc":"1998 BOEING 737-724"},"7CE":{"r":"N13718","t":"B737","f":"00","desc":"1999 BOEING 737-724"},"7CF":{"r":"N13719","t":"C172","f":"00","desc":""},"7D0":{"r":"N1372","t":"GLID","f":"00","desc":""},"7D1":{"r":"N1372A","t":"PA18","f":"00","desc":""},"7D2":{"r":"N1372B","t":"L8","f":"00","desc":""},"7D5":{"r":"N1372E","t":"C172","f":"00","desc":"1978 CESSNA 172N"},"7D8":{"r":"N1372H","t":"AR15","f":"00","desc":""},"7E0":{"r":"N1372R","t":"AA1","f":"00","desc":""},"7E2":{"r":"N1372T","t":"ACR2","f":"00","desc":""},"7E3":{"r":"N1372U","t":"C172","f":"00","desc":""},"7E9":{"r":"N13720","t":"B737","f":"00","desc":"1999 BOEING 737-724"},"7EA":{"r":"N13721","t":"C172","f":"00","desc":"Cessna 172M Skyhawk"},"7EC":{"r":"N13723","t":"C172","f":"00","desc":"Cessna 172M Skyhawk"},"7EE":{"r":"N13725","t":"C172","f":"00","desc":"1974 CESSNA 172M"},"7F0":{"r":"N13727","t":"C172","f":"00","desc":""},"7F4":{"r":"N1373A","t":"B763","f":"00","desc":""},"7F5":{"r":"N1373B","t":"L8","f":"00","desc":""},"7F6":{"r":"N1373C","t":"C177","f":"00","desc":""},"7F8":{"r":"N1373E","t":"C172","f":"00","desc":""},"7F9":{"r":"N1373F","t":"C185","f":"00","desc":"Cessna A185F Skywagon 185"},"7FA":{"r":"N1373G","t":"C340","f":"00","desc":""},"7FE":{"r":"VT-CAM","t":"C172","f":"00","desc":"Cessna 172R Skyhawk"},"7FF":{"r":"N1373M","t":"C77R","f":"00","desc":"1971 CESSNA 177RG"},"803":{"r":"N1373R","t":"AA1","f":"00","desc":""},"806":{"r":"N1373U","t":"C172","f":"00","desc":"Cessna 172M Skyhawk"},"808":{"r":"N1373W","t":"M20P","f":"00","desc":""},"80B":{"r":"N1373Z","t":"BE95","f":"00","desc":""},"80D":{"r":"N13731","t":"C172","f":"00","desc":"Cessna 172M Skyhawk"},"80E":{"r":"N13732","t":"C172","f":"00","desc":"Cessna 172M Skyhawk"},"80F":{"r":"N13733","t":"C177","f":"00","desc":"1976 CESSNA 177B"},"810":{"r":"N13734","t":"C177","f":"00","desc":"1976 CESSNA 177B"},"813":{"r":"N13737","t":"C172","f":"00","desc":"Cessna 172M Skyhawk"},"815":{"r":"N13739","t":"C172","f":"00","desc":""},"816":{"r":"N1374","t":"GLID","f":"00","desc":""},"81A":{"r":"N1374D","t":"ULAC","f":"00","desc":""},"81B":{"r":"N1374E","t":"C172","f":"00","desc":""},"81C":{"r":"N1374F","t":"C172","f":"00","desc":""},"81F":{"r":"N1374J","t":"AC11","f":"00","desc":""},"821":{"r":"N1374L","t":"COL4","f":"00","desc":"2006 COLUMBIA AIRCRAFT MFG LC41-550FG"},"825":{"r":"N1374Q","t":"C150","f":"00","desc":"Cessna 150L"},"827":{"r":"N1374S","t":"C182","f":"00","desc":""},"828":{"r":"N1374T","t":"ULAC","f":"00","desc":""},"829":{"r":"N1374U","t":"C172","f":"00","desc":""},"82B":{"r":"N1374W","t":"M20P","f":"00","desc":""},"82C":{"r":"N1374X","t":"B47G","f":"00","desc":""},"82D":{"r":"N1374Y","t":"C172","f":"00","desc":"1961 CESSNA 172C"},"82F":{"r":"N13740","t":"C177","f":"00","desc":""},"836":{"r":"N13747","t":"C177","f":"00","desc":"Cessna 177B Cardinal"},"837":{"r":"N13748","t":"C172","f":"00","desc":"1974 CESSNA 172M"},"839":{"r":"N1375","t":"DRON","f":"00","desc":""},"83B":{"r":"N1375B","t":"BD5","f":"00","desc":""},"83C":{"r":"N1375C","t":"C177","f":"00","desc":"1977 CESSNA 177B"},"83F":{"r":"N1375F","t":"AT3T","f":"00","desc":""},"841":{"r":"N1375H","t":"GLAS","f":"00","desc":""},"842":{"r":"N1375J","t":"AC11","f":"00","desc":"1975 ROCKWELL INTERNATIONAL 112A"},"843":{"r":"N1375K","t":"BLKS","f":"00","desc":""},"844":{"r":"N1375L","t":"C337","f":"00","desc":"1978 CESSNA T337H"},"846":{"r":"N1375N","t":"SPR2","f":"00","desc":""},"84E":{"r":"N1375W","t":"M20P","f":"00","desc":""},"852":{"r":"N13750","t":"B737","f":"00","desc":"1999 BOEING 737-724"},"853":{"r":"N13751","t":"C172","f":"00","desc":"1974 CESSNA 172M"},"854":{"r":"N13752","t":"C172","f":"00","desc":""},"855":{"r":"N13753","t":"C172","f":"00","desc":""},"856":{"r":"N13754","t":"C172","f":"00","desc":"1974 CESSNA 172M"},"858":{"r":"N13756","t":"C177","f":"00","desc":"Cessna 177B Cardinal"},"859":{"r":"N13757","t":"C177","f":"00","desc":"1976 CESSNA 177B"},"85D":{"r":"N1376A","t":"BE36","f":"00","desc":"1969 BEECH 36"},"862":{"r":"N1376F","t":"C172","f":"00","desc":"172"},"863":{"r":"N1376G","t":"C402","f":"00","desc":"1980 CESSNA 402C"},"865":{"r":"N1376J","t":"AC11","f":"00","desc":"1975 ROCKWELL INTERNATIONAL 112A"},"868":{"r":"N1376M","t":"C182","f":"00","desc":"Cessna 182P Skylane"},"86B":{"r":"N1376Q","t":"C150","f":"00","desc":""},"86C":{"r":"N1376R","t":"AA5","f":"00","desc":"1975 GRUMMAN AMERICAN AVN. CORP. AA-5"},"86D":{"r":"N1376S","t":"C182","f":"00","desc":"Cessna 182P Skylane"},"86E":{"r":"N1376T","t":"P28A","f":"00","desc":"Piper PA-28 140 Cherokee E"},"870":{"r":"N1376V","t":"C206","f":"00","desc":"2007 CESSNA T206H"},"871":{"r":"N1376W","t":"M20P","f":"00","desc":""},"875":{"r":"N13760","t":"PA27","f":"00","desc":""},"879":{"r":"N13764","t":"PA27","f":"00","desc":"Piper PA-23 Aztec 250D"},"880":{"r":"N1377A","t":"PA18","f":"00","desc":"PIPER PA-18-125"},"881":{"r":"N1377B","t":"","f":"00","desc":""},"882":{"r":"N1377C","t":"C177","f":"00","desc":""},"883":{"r":"N1377D","t":"C170","f":"00","desc":""},"884":{"r":"N1377E","t":"C172","f":"00","desc":""},"885":{"r":"N1377F","t":"C172","f":"00","desc":""},"887":{"r":"N1377H","t":"P28A","f":"00","desc":""},"888":{"r":"N1377J","t":"AC11","f":"00","desc":""},"88B":{"r":"N1377M","t":"C172","f":"00","desc":"Cessna 172L Skyhawk"},"88F":{"r":"N1377R","t":"AA5","f":"00","desc":""},"890":{"r":"N1377S","t":"C172","f":"00","desc":"Cessna 172S"},"891":{"r":"N1377T","t":"P28A","f":"00","desc":"Piper PA-28 140 Cherokee E"},"892":{"r":"N1377U","t":"C172","f":"00","desc":"Cessna 172M Skyhawk"},"897":{"r":"N1377Z","t":"BE55","f":"00","desc":""},"89E":{"r":"N13776","t":"","f":"00","desc":""},"89F":{"r":"N13777","t":"ZZZZ","f":"00","desc":""},"8A0":{"r":"N13778","t":"C172","f":"00","desc":""},"8A3":{"r":"N1378A","t":"PA18","f":"00","desc":""},"8A6":{"r":"N1378D","t":"C170","f":"00","desc":""},"8AA":{"r":"N1378H","t":"AR15","f":"00","desc":""},"8AB":{"r":"N1378J","t":"ULAC","f":"00","desc":""},"8AC":{"r":"N1378K","t":"L8","f":"00","desc":""},"8AE":{"r":"N1378M","t":"C172","f":"00","desc":""},"8B1":{"r":"N1378Q","t":"C150","f":"00","desc":""},"8B3":{"r":"N1378S","t":"C182","f":"00","desc":"1976 CESSNA 182P"},"8B7":{"r":"N1378W","t":"M20P","f":"00","desc":""},"8B8":{"r":"N1378X","t":"LGEZ","f":"00","desc":""},"8C1":{"r":"N13786","t":"C172","f":"00","desc":""},"8C2":{"r":"N13787","t":"ST75","f":"00","desc":""},"8C7":{"r":"N1379B","t":"RV3","f":"00","desc":""},"8C9":{"r":"N1379D","t":"C170","f":"00","desc":""},"8CC":{"r":"N1379G","t":"C340","f":"00","desc":""},"8D6":{"r":"N1379S","t":"C182","f":"00","desc":"1976 CESSNA 182P"},"8D7":{"r":"N1379T","t":"P28A","f":"00","desc":""},"8D8":{"r":"N1379U","t":"C172","f":"00","desc":""},"8D9":{"r":"N1379V","t":"ST75","f":"00","desc":""},"8E2":{"r":"N13794","t":"WAIX","f":"00","desc":""},"8E4":{"r":"N13796","t":"C172","f":"00","desc":"1974 CESSNA 172M"},"8E9":{"r":"N138A","t":"LEG2","f":"00","desc":"Lancair International Lancair Legacy"},"8EB":{"r":"N138AB","t":"PA25","f":"00","desc":""},"8EC":{"r":"N138AC","t":"BL8","f":"00","desc":""},"8ED":{"r":"N138AD","t":"BE33","f":"00","desc":"1991 BEECH F33A"},"8EE":{"r":"N138AE","t":"B06","f":"00","desc":"1983 BELL HELICOPTER TEXTRON 206L-1"},"8EF":{"r":"N138AF","t":"COL4","f":"00","desc":"2006 COLUMBIA AIRCRAFT MFG LC41-550FG"},"8F5":{"r":"N138AM","t":"P38","f":"00","desc":""},"8F6":{"r":"N138AN","t":"A321","f":"00","desc":"2015 AIRBUS A321-231"},"8F7":{"r":"N138AP","t":"ULAC","f":"00","desc":""},"8F9":{"r":"N138AR","t":"S61","f":"00","desc":"Sikorsky S-61 N"},"8FA":{"r":"N138AS","t":"GLID","f":"00","desc":""},"901":{"r":"N138AZ","t":"C182","f":"00","desc":"Cessna T182T Turbo Skylane"},"903":{"r":"N138BA","t":"ULAC","f":"00","desc":""},"905":{"r":"N138BC","t":"P28A","f":"00","desc":"2003 PIPER PA-28-181"},"908":{"r":"N138BF","t":"CRUZ","f":"00","desc":""},"909":{"r":"N138BG","t":"C680","f":"00","desc":"Cessna 680 Citation Sovereign"},"912":{"r":"N138BR","t":"TAMP","f":"00","desc":""},"913":{"r":"N138BS","t":"ULAC","f":"00","desc":""},"91B":{"r":"N138C","t":"WAIX","f":"00","desc":""},"91C":{"r":"N138CA","t":"C55B","f":"00","desc":"1999 CESSNA 550"},"91E":{"r":"N138CC","t":"PA18","f":"00","desc":"CubCrafters CC18-180 Top Cub"},"922":{"r":"N138CG","t":"","f":"00","desc":""},"923":{"r":"N138CH","t":"CL30","f":"00","desc":"2008 BOMBARDIER INC BD-100-1A10"},"925":{"r":"N138CK","t":"SR22","f":"00","desc":"2009 CIRRUS DESIGN CORP SR22"},"926":{"r":"N138CL","t":"DV20","f":"00","desc":"1998 DIAMOND AIRCRAFT IND INC DA20-C1"},"927":{"r":"N138CM","t":"P46T","f":"00","desc":"2010 PIPER AIRCRAFT INC PA46R-350T"},"929":{"r":"N138CP","t":"M7","f":"00","desc":"Maule MT-7 235 Super Rocket"},"92B":{"r":"N138CR","t":"SR22","f":"00","desc":"2005 CIRRUS DESIGN CORP SR22"},"92C":{"r":"N138CS","t":"FOX","f":"00","desc":""},"92D":{"r":"N138CT","t":"FDCT","f":"00","desc":""},"930":{"r":"N138CW","t":"BALL","f":"00","desc":""},"934":{"r":"N138D","t":"RV6","f":"00","desc":""},"936":{"r":"N138DB","t":"RV6","f":"00","desc":""},"937":{"r":"N138DC","t":"P28A","f":"00","desc":"2001 PIPER PA-28-161"},"939":{"r":"N138DE","t":"E145","f":"01","desc":"Embraer EMB-145LR"},"93C":{"r":"N138DH","t":"SONX","f":"00","desc":""},"93D":{"r":"N138DJ","t":"WAIX","f":"00","desc":""},"940":{"r":"N138DM","t":"CL60","f":"00","desc":"2007 BOMBARDIER INC CL-600-2B16"},"945":{"r":"N138DS","t":"DA40","f":"00","desc":""},"949":{"r":"N138DW","t":"RV6","f":"00","desc":""},"94D":{"r":"N138E","t":"SKRA","f":"00","desc":""},"959":{"r":"N138EM","t":"L39","f":"00","desc":"Aero Vodochody L-39 C"},"95F":{"r":"N138ET","t":"RV6","f":"00","desc":""},"961":{"r":"N138EV","t":"CRJ9","f":"00","desc":"2009 BOMBARDIER INC CL-600-2D24"},"965":{"r":"N138EZ","t":"DEFI","f":"00","desc":""},"969":{"r":"N138FC","t":"P28A","f":"00","desc":"PA-28"},"96B":{"r":"N138FE","t":"B763","f":"00","desc":"Boeing 767 3S2F"},"96F":{"r":"N138FJ","t":"F2TH","f":"00","desc":"Dassault Falcon 2000"},"971":{"r":"N138FL","t":"ULAC","f":"00","desc":""},"976":{"r":"N138FR","t":"C172","f":"00","desc":""},"977":{"r":"N138FS","t":"DC3","f":"00","desc":"1942 DOUGLAS DC3C"},"97F":{"r":"N138G","t":"BE35","f":"00","desc":"1964 BEECH S35"},"981":{"r":"N138GB","t":"BL8","f":"00","desc":""},"98A":{"r":"N138GL","t":"GLF5","f":"00","desc":"2014 GULFSTREAM AEROSPACE GV-SP (G550)"},"98B":{"r":"N138GM","t":"GLST","f":"00","desc":"2013 MINERVA FAMILY LIMITED PTNRSP SPORTSMAN GS-2"},"98D":{"r":"N138GP","t":"GP4","f":"00","desc":""},"998":{"r":"N138H","t":"FOX","f":"00","desc":""},"9A5":{"r":"N138HN","t":"EC35","f":"00","desc":""},"9A7":{"r":"N138HQ","t":"E170","f":"00","desc":"2008 EMBRAER-EMPRESA BRASILEIRA DE ERJ 170-200 LR"},"9AD":{"r":"N138HW","t":"C56X","f":"00","desc":"2001 CESSNA 560XL"},"9B3":{"r":"N138JB","t":"ULAC","f":"00","desc":""},"9B7":{"r":"N138JF","t":"RV8","f":"00","desc":""},"9B8":{"r":"N138JG","t":"C421","f":"00","desc":""},"9BA":{"r":"N138JJ","t":"C140","f":"00","desc":""},"9BD":{"r":"N138JM","t":"TBM7","f":"00","desc":""},"9BF":{"r":"N138JP","t":"C177","f":"00","desc":""},"9C2":{"r":"N138JS","t":"GLID","f":"00","desc":""},"9D5":{"r":"N138KL","t":"TB30","f":"00","desc":""},"9DE":{"r":"N138KV","t":"C680","f":"00","desc":"Cessna Citation Sovereign"},"9E3":{"r":"N138L","t":"DSA1","f":"00","desc":""},"9EA":{"r":"N138LG","t":"HROC","f":"00","desc":""},"9F0":{"r":"N138LN","t":"EC35","f":"00","desc":"2004 EUROCOPTER DEUTSCHLAND GMBH EC 135 P2+"},"9F4":{"r":"N138LS","t":"FDCT","f":"00","desc":""},"9F8":{"r":"N138LW","t":"BN2P","f":"00","desc":""},"9FC":{"r":"N138M","t":"FDCT","f":"00","desc":"2014 FLIGHT DESIGN GMBH CTLS"},"9FD":{"r":"N138MA","t":"TBM8","f":"00","desc":"2012 SOCATA TBM 700"},"9FE":{"r":"N138MB","t":"CH7A","f":"00","desc":"BELLANCA 7ACA"},"9FF":{"r":"N138MC","t":"SR22","f":"00","desc":""},"A01":{"r":"N138ME","t":"C172","f":"00","desc":"Cessna 172S Skyhawk SP"},"A02":{"r":"N138MF","t":"SR20","f":"00","desc":""},"A04":{"r":"N138MH","t":"EC35","f":"00","desc":"EUROCOPTER DEUTSCHLAND GMBH EC135T2"},"A16":{"r":"N138NA","t":"ULAC","f":"00","desc":""},"A26":{"r":"N138NS","t":"GALX","f":"00","desc":""},"A27":{"r":"N138NT","t":"RV12","f":"00","desc":""},"A2E":{"r":"N138P","t":"BDOG","f":"00","desc":""},"A2F":{"r":"N138PA","t":"LNC2","f":"00","desc":"1996 W L PERRY DBA AAA HELI SERVICE LANCAIR 360"},"A30":{"r":"N138PB","t":"BE58","f":"00","desc":"Beech Baron 58P"},"A31":{"r":"N138PC","t":"DRON","f":"00","desc":""},"A32":{"r":"N138PD","t":"B407","f":"00","desc":""},"A35":{"r":"N138PG","t":"S22T","f":"00","desc":"2013 CIRRUS DESIGN CORP SR22T"},"A36":{"r":"N138PH","t":"EC30","f":"00","desc":"2004 EUROCOPTER EC 130 B4"},"A39":{"r":"N138PL","t":"BE58","f":"00","desc":""},"A3A":{"r":"N138PM","t":"RV8","f":"00","desc":""},"A3F":{"r":"N138PS","t":"PC12","f":"00","desc":"Pilatus PC-XII NG 47E"},"A47":{"r":"N138Q","t":"BE55","f":"00","desc":"1964 BEECH 95-B55 (T42A)"},"A60":{"r":"N138R","t":"PA31","f":"00","desc":""},"A62":{"r":"N138RB","t":"DRON","f":"00","desc":""},"A63":{"r":"N138RC","t":"C77R","f":"00","desc":"Cessna 177 Cardinal RG"},"A69":{"r":"N138RJ","t":"TOBA","f":"00","desc":"1988 SOCATA TB 10"},"A6A":{"r":"N138RK","t":"AVID","f":"00","desc":""},"A6C":{"r":"N138RM","t":"C337","f":"00","desc":""},"A70":{"r":"N138RR","t":"T28","f":"00","desc":"NORTH AMERICAN T-28B"},"A71":{"r":"N138RS","t":"ULAC","f":"00","desc":""},"A74":{"r":"N138RV","t":"RV8","f":"00","desc":""},"A7A":{"r":"N138SA","t":"C500","f":"00","desc":"Cessna Citation I"},"A7B":{"r":"N138SB","t":"KRIC","f":"00","desc":""},"A7C":{"r":"N138SC","t":"PTS1","f":"00","desc":"Amateur Built Pitts Special S-1D"},"A7D":{"r":"N138SD","t":"","f":"00","desc":""},"A7E":{"r":"N138SE","t":"PARA","f":"00","desc":""},"A7F":{"r":"N138SF","t":"P28A","f":"00","desc":"1965 PIPER PA-28-140"},"A81":{"r":"N138SH","t":"DRON","f":"00","desc":""},"A82":{"r":"N138SJ","t":"PRM1","f":"00","desc":"RAYTHEON AIRCRAFT COMPANY 390"},"A87":{"r":"N138SP","t":"C750","f":"00","desc":"2000 CESSNA 750"},"A8B":{"r":"N138ST","t":"PARA","f":"00","desc":""},"A8E":{"r":"N138SW","t":"C182","f":"00","desc":"Cessna 182Q Skylane"},"A90":{"r":"N138SY","t":"E170","f":"00","desc":"2015 EMBRAER S A ERJ170-200LR"},"A92":{"r":"N138T","t":"BE35","f":"00","desc":"1950 BEECH B35"},"A95":{"r":"N138TC","t":"BALL","f":"00","desc":""},"A9D":{"r":"N138TL","t":"BE55","f":"00","desc":"Beech Baron D55"},"A9E":{"r":"N138TM","t":"ULAC","f":"00","desc":""},"AA0":{"r":"N138TP","t":"P28A","f":"00","desc":"1968 PIPER PA-28-140"},"AA6":{"r":"N138TV","t":"PC12","f":"00","desc":"2011 PILATUS AIRCRAFT LTD PC-12\/47E"},"AA7":{"r":"N138TW","t":"BE35","f":"00","desc":""},"AA8":{"r":"N138TX","t":"H500","f":"00","desc":"1979 HUGHES 369D"},"AAF":{"r":"N138UD","t":"C172","f":"00","desc":"Cessna 172S Skyhawk SP"},"AB3":{"r":"N138UH","t":"DRON","f":"00","desc":""},"AB9":{"r":"N138UP","t":"A306","f":"00","desc":"2001 AIRBUS INDUSTRIE A300F4-622R"},"AC4":{"r":"N138V","t":"ULAC","f":"00","desc":""},"AC6":{"r":"N138VB","t":"C240","f":"00","desc":""},"ADD":{"r":"N138W","t":"ULAC","f":"00","desc":""},"AE5":{"r":"N138WH","t":"H500","f":"00","desc":"1981 HUGHES 369D"},"AE6":{"r":"N138WJ","t":"EUPA","f":"00","desc":""},"AF2":{"r":"N138WW","t":"C170","f":"00","desc":""},"AFB":{"r":"N138XE","t":"UHEL","f":"00","desc":""},"B0F":{"r":"N138Y","t":"P46T","f":"00","desc":""},"B3E":{"r":"N138ZX","t":"ULAC","f":"00","desc":""},"B42":{"r":"N1380A","t":"PA18","f":"00","desc":""},"B44":{"r":"N1380C","t":"S108","f":"00","desc":"1946 STINSON 108"},"B48":{"r":"N1380G","t":"C340","f":"00","desc":"1976 CESSNA 340A"},"B4A":{"r":"N1380J","t":"AC11","f":"00","desc":""},"B4B":{"r":"N1380K","t":"L8","f":"00","desc":"1946 LUSCOMBE 8A"},"B4F":{"r":"N1380P","t":"KR1","f":"00","desc":""},"B51":{"r":"N1380R","t":"AA1","f":"00","desc":""},"B53":{"r":"N1380T","t":"PA34","f":"00","desc":""},"B54":{"r":"N1380U","t":"C172","f":"00","desc":"Cessna 172M Skyhawk"},"B56":{"r":"N1380W","t":"M20P","f":"00","desc":"Mooney M.20C Mark 21"},"B57":{"r":"N1380X","t":"B47G","f":"00","desc":""},"B5B":{"r":"N13801","t":"ZZZZ","f":"00","desc":""},"B5C":{"r":"N13802","t":"PA18","f":"00","desc":""},"B5D":{"r":"N13803","t":"PA27","f":"00","desc":"1969 PIPER PA-23-250"},"B5E":{"r":"N13804","t":"C177","f":"00","desc":""},"B5F":{"r":"N13805","t":"C172","f":"00","desc":""},"B60":{"r":"N13806","t":"C172","f":"00","desc":"Cessna 172M Skyhawk"},"B61":{"r":"N13807","t":"C172","f":"00","desc":""},"B64":{"r":"N1381","t":"PTS1","f":"00","desc":"1967 PITTS S-1C"},"B65":{"r":"N1381A","t":"B763","f":"00","desc":"Boeing 767 316ER\/W"},"B67":{"r":"N1381C","t":"C177","f":"00","desc":""},"B6A":{"r":"N1381F","t":"C172","f":"00","desc":""},"B6C":{"r":"N1381H","t":"AR15","f":"00","desc":""},"B6E":{"r":"N1381K","t":"L8","f":"00","desc":""},"B72":{"r":"N1381P","t":"PA23","f":"00","desc":""},"B79":{"r":"N1381W","t":"M20P","f":"00","desc":"Mooney M.20C Mark 21"},"B7D":{"r":"N13810","t":"C172","f":"00","desc":"Cessna 172M Skyhawk"},"B7E":{"r":"N13811","t":"J3","f":"00","desc":""},"B81":{"r":"N13814","t":"PA18","f":"00","desc":""},"B84":{"r":"N13817","t":"PA27","f":"00","desc":""},"B86":{"r":"N13819","t":"C177","f":"00","desc":""},"B8A":{"r":"N1382C","t":"SR22","f":"00","desc":"2003 CIRRUS DESIGN CORP SR22"},"B8D":{"r":"N1382F","t":"C172","f":"00","desc":""},"B8F":{"r":"N1382H","t":"P28A","f":"00","desc":""},"B91":{"r":"N1382K","t":"L8","f":"00","desc":""},"B93":{"r":"N1382M","t":"C182","f":"00","desc":""},"B96":{"r":"N1382Q","t":"C150","f":"00","desc":""},"B99":{"r":"N1382T","t":"P28A","f":"00","desc":""},"B9B":{"r":"N1382V","t":"COL4","f":"00","desc":"2006 COLUMBIA AIRCRAFT MFG LC41-550FG"},"BA1":{"r":"N13821","t":"C172","f":"00","desc":"Cessna 172M Skyhawk"},"BA2":{"r":"N13822","t":"ZZZZ","f":"00","desc":""},"BA4":{"r":"N13824","t":"PA18","f":"00","desc":"1954 PIPER L-21B"},"BAD":{"r":"N1383C","t":"PA18","f":"00","desc":""},"BB1":{"r":"N1383G","t":"C340","f":"00","desc":""},"BB3":{"r":"N1383J","t":"AC11","f":"00","desc":""},"BBD":{"r":"N1383U","t":"C172","f":"00","desc":"Cessna 172M Skyhawk"},"BBE":{"r":"N1383V","t":"ST75","f":"00","desc":""},"BBF":{"r":"N1383W","t":"PA18","f":"00","desc":""},"BC3":{"r":"N13830","t":"C172","f":"00","desc":""},"BC5":{"r":"N13832","t":"PA27","f":"00","desc":""},"BC6":{"r":"N13833","t":"PA18","f":"00","desc":""},"BC7":{"r":"N13834","t":"C172","f":"00","desc":""},"BCC":{"r":"N13839","t":"PA27","f":"00","desc":"Piper PA-23 Aztec 250D"},"BD0":{"r":"N1384C","t":"C177","f":"00","desc":""},"BD3":{"r":"N1384F","t":"AVID","f":"00","desc":""},"BD5":{"r":"N1384H","t":"AR15","f":"00","desc":"1949 AERONCA 15AC"},"BD8":{"r":"N1384L","t":"C337","f":"00","desc":""},"BDB":{"r":"N1384P","t":"PA23","f":"00","desc":""},"BDE":{"r":"N1384S","t":"C182","f":"00","desc":""},"BE2":{"r":"N1384W","t":"M20P","f":"00","desc":"Mooney M.20C Mark 21"},"BE3":{"r":"N1384X","t":"ULAC","f":"00","desc":""},"BED":{"r":"N13847","t":"RELI","f":"00","desc":""},"BEF":{"r":"N13849","t":"C172","f":"00","desc":""},"BF3":{"r":"N1385C","t":"PA18","f":"00","desc":""},"BF5":{"r":"N1385E","t":"CH7A","f":"00","desc":""},"BF6":{"r":"N1385F","t":"C172","f":"00","desc":""},"BFB":{"r":"N1385L","t":"C337","f":"00","desc":""},"BFC":{"r":"N1385M","t":"C182","f":"00","desc":""},"BFF":{"r":"N1385Q","t":"C150","f":"00","desc":""},"C00":{"r":"N1385R","t":"AA5","f":"00","desc":"Grumman American AA-5 Traveler"},"C02":{"r":"N1385T","t":"P28R","f":"00","desc":"Piper PA-28R 200 Cherokee Arrow II"},"C04":{"r":"N1385V","t":"C303","f":"00","desc":"Cessna T303 Crusader"},"C08":{"r":"N1385Z","t":"BE95","f":"00","desc":""},"C0C":{"r":"N13853","t":"RELI","f":"00","desc":""},"C0D":{"r":"N13854","t":"PA11","f":"00","desc":"Texas Sport Aircraft TX-11"},"C0E":{"r":"N13855","t":"RELI","f":"00","desc":"1934 STINSON SR-5B"},"C11":{"r":"N13858","t":"PA18","f":"00","desc":""},"C14":{"r":"N1386A","t":"PA18","f":"00","desc":"1951 PIPER PA-18-125"},"C16":{"r":"N1386C","t":"P2","f":"00","desc":""},"C17":{"r":"N1386D","t":"C170","f":"00","desc":""},"C18":{"r":"N1386E","t":"C182","f":"00","desc":"1982 CESSNA 182R"},"C1B":{"r":"N1386H","t":"P28A","f":"00","desc":"Piper PA-28 181 Archer II"},"C1C":{"r":"N1386J","t":"AC11","f":"00","desc":""},"C1F":{"r":"N1386M","t":"C182","f":"00","desc":""},"C22":{"r":"N1386Q","t":"C150","f":"00","desc":"Cessna 150L"},"C24":{"r":"N1386S","t":"C182","f":"00","desc":"Cessna 182P Skylane"},"C25":{"r":"N1386T","t":"P28R","f":"00","desc":"2003 PIPER PA-28R-201"},"C2A":{"r":"N1386Y","t":"ULAC","f":"00","desc":""},"C2E":{"r":"N13862","t":"PA27","f":"00","desc":"1970 PIPER PA-23-250"},"C2F":{"r":"N13863","t":"PA18","f":"00","desc":"Piper PA-18 150 Super Cub"},"C31":{"r":"N13865","t":"PA27","f":"00","desc":""},"C3C":{"r":"N1387F","t":"C172","f":"00","desc":""},"C3D":{"r":"N1387G","t":"PA18","f":"00","desc":""},"C3E":{"r":"N1387H","t":"AR15","f":"00","desc":""},"C42":{"r":"N1387M","t":"C182","f":"00","desc":"Cessna 182P Skylane"},"C43":{"r":"N1387N","t":"T6","f":"00","desc":""},"C45":{"r":"N1387Q","t":"C150","f":"00","desc":"1971 CESSNA 150L"},"C47":{"r":"N1387S","t":"C182","f":"00","desc":""},"C49":{"r":"N1387U","t":"C172","f":"00","desc":"Cessna 172M Skyhawk"},"C4A":{"r":"N1387V","t":"ST75","f":"00","desc":""},"C4D":{"r":"N1387Y","t":"C172","f":"00","desc":"1961 CESSNA 172C"},"C51":{"r":"N13872","t":"RELI","f":"00","desc":""},"C53":{"r":"N13874","t":"C172","f":"00","desc":"Cessna 172M Skyhawk"},"C59":{"r":"N1388","t":"MIMU","f":"00","desc":""},"C5A":{"r":"N1388A","t":"GYRO","f":"00","desc":""},"C5B":{"r":"N1388B","t":"L8","f":"00","desc":""},"C5C":{"r":"N1388C","t":"GYRO","f":"00","desc":""},"C5D":{"r":"N1388D","t":"C170","f":"00","desc":""},"C68":{"r":"N1388Q","t":"GYRO","f":"00","desc":""},"C69":{"r":"N1388R","t":"AA5","f":"00","desc":"1975 GRUMMAN AMERICAN AVN. CORP. AA-5"},"C6A":{"r":"N1388S","t":"C182","f":"00","desc":"Cessna 182P Skylane"},"C6B":{"r":"N1388T","t":"P28A","f":"00","desc":""},"C6C":{"r":"N1388U","t":"C172","f":"00","desc":""},"C6E":{"r":"N1388W","t":"M20P","f":"00","desc":""},"C72":{"r":"N13880","t":"PA18","f":"00","desc":"1974 PIPER PA-18-150"},"C74":{"r":"N13882","t":"PA27","f":"00","desc":"1970 PIPER PA-23-250"},"C76":{"r":"N13884","t":"C172","f":"00","desc":""},"C79":{"r":"N13887","t":"C172","f":"00","desc":"Cessna 172M Skyhawk"},"C7B":{"r":"N13889","t":"C172","f":"00","desc":"Cessna 172M Skyhawk"},"C7D":{"r":"N1389A","t":"PA18","f":"00","desc":"1951 PIPER PA-18"},"C7E":{"r":"N1389B","t":"C182","f":"00","desc":"2005 CESSNA T182T"},"C81":{"r":"N1389E","t":"CH7A","f":"00","desc":""},"C82":{"r":"N1389F","t":"C172","f":"00","desc":""},"C84":{"r":"N1389H","t":"P28R","f":"00","desc":"Piper PA-28R 201T Turbo Arrow III"},"C8E":{"r":"N1389T","t":"P28A","f":"00","desc":"Piper PA-28 180 Cherokee G"},"C94":{"r":"N1389Z","t":"BE35","f":"00","desc":"1961 BEECH N35"},"C95":{"r":"N13890","t":"C172","f":"00","desc":"Cessna 172M"},"C97":{"r":"N13892","t":"C177","f":"00","desc":""},"C99":{"r":"N13894","t":"WACO","f":"00","desc":""},"C9A":{"r":"N13895","t":"PA18","f":"00","desc":"1974 PIPER PA-18-150"},"C9C":{"r":"N13897","t":"WACC","f":"00","desc":"1934 WACO UKC"},"CA0":{"r":"N139A","t":"CH7A","f":"00","desc":""},"CA1":{"r":"N139AA","t":"RALL","f":"00","desc":""},"CA2":{"r":"N139AB","t":"PARA","f":"00","desc":""},"CA3":{"r":"N139AC","t":"BL8","f":"00","desc":""},"CA5":{"r":"N139AE","t":"B06","f":"00","desc":"Bell 206L Long Ranger"},"CA7":{"r":"N139AG","t":"R22","f":"00","desc":""},"CA8":{"r":"N139AH","t":"AVID","f":"00","desc":""},"CA9":{"r":"N139AJ","t":"L39","f":"00","desc":""},"CAA":{"r":"N139AK","t":"A139","f":"00","desc":"2005 AGUSTA SPA AB139"},"CAC":{"r":"N139AM","t":"EC35","f":"00","desc":"EC-135"},"CAD":{"r":"N139AN","t":"A321","f":"00","desc":"2015 AIRBUS A321-231"},"CAE":{"r":"N139AP","t":"ULAC","f":"00","desc":""},"CB1":{"r":"N139AS","t":"SZ45","f":"00","desc":"1978 PDPS PZL-BIELSKO SZD-45A OGAR"},"CBA":{"r":"N139BA","t":"ULAC","f":"00","desc":""},"CBB":{"r":"N139BB","t":"T210","f":"00","desc":"T.210"},"CBC":{"r":"N139BC","t":"BL8","f":"00","desc":""},"CBF":{"r":"N139BF","t":"CRUZ","f":"00","desc":""},"CC0":{"r":"N139BG","t":"GLID","f":"00","desc":"1984 BURKHART GROB G 103 TWIN II"},"CC2":{"r":"N139BJ","t":"L39","f":"00","desc":"L-39"},"CCA":{"r":"N139BS","t":"RV3","f":"00","desc":""},"CD3":{"r":"N139CA","t":"PA24","f":"00","desc":"1966 PIPER PA-24-260"},"CD5":{"r":"N139CC","t":"S76","f":"00","desc":"Sikorsky S-76 B"},"CDA":{"r":"N139CH","t":"A139","f":"00","desc":"AgustaWestland AW.139"},"CDB":{"r":"N139CJ","t":"C25B","f":"00","desc":"Cessna Citation CJ3"},"CDC":{"r":"N139CK","t":"L39","f":"00","desc":""},"CDE":{"r":"N139CM","t":"L39","f":"00","desc":""},"CDF":{"r":"N139CN","t":"A139","f":"00","desc":"AGUSTA SPA AW139"},"CE0":{"r":"N139CP","t":"M7","f":"00","desc":""},"CE3":{"r":"N139CS","t":"PAY1","f":"00","desc":""},"CE4":{"r":"N139CT","t":"FDCT","f":"00","desc":""},"CE7":{"r":"N139CW","t":"A139","f":"00","desc":"2005 AGUSTA SPA AB139"},"CEB":{"r":"N139D","t":"DV20","f":"00","desc":""},"CEC":{"r":"N139DA","t":"DV20","f":"00","desc":"2012 DIAMOND AIRCRAFT IND INC DA20-C1"},"CED":{"r":"N139DB","t":"PA27","f":"00","desc":"PIPER PA-23-250"},"CEE":{"r":"N139DC","t":"COL4","f":"00","desc":"LANCAIR COMPANY LC41-550FG"},"CF0":{"r":"N139DE","t":"A139","f":"00","desc":"2013 AGUSTAWESTLAND PHILADELPHIA AW139"},"CF1":{"r":"N139DF","t":"L39","f":"00","desc":"AERO VODOCHODY L-39"},"CF7":{"r":"N139DM","t":"P28R","f":"00","desc":"Piper PA-28R 200 Cherokee Arrow"},"CFD":{"r":"N139DT","t":"PARA","f":"00","desc":"1998 BUCKEYE AVIATION DREAM MACHINE ''98"},"D03":{"r":"N139DZ","t":"L39","f":"00","desc":""},"D04":{"r":"N139E","t":"WACO","f":"00","desc":""},"D0C":{"r":"N139EH","t":"A139","f":"00","desc":"Agusta-Bell AB.139"},"D11":{"r":"N139EN","t":"L39","f":"00","desc":"1979 AERO VODOCHODY L39C"},"D14":{"r":"N139ER","t":"C172","f":"00","desc":"Cessna 172Q Cutlass"},"D15":{"r":"N139ES","t":"L39","f":"01","desc":"Aero Vodochody L-39C \"Bitcoin Jet\""},"D1A":{"r":"N139EX","t":"A139","f":"00","desc":""},"D1C":{"r":"N139EZ","t":"VEZE","f":"00","desc":""},"D20":{"r":"N139FC","t":"P28A","f":"00","desc":""},"D22":{"r":"N139FE","t":"B763","f":"00","desc":"Boeing 767 300F"},"D28":{"r":"N139FL","t":"ULAC","f":"00","desc":""},"D2B":{"r":"N139FP","t":"WAIX","f":"00","desc":""},"D2E":{"r":"N139FS","t":"L39","f":"00","desc":""},"D32":{"r":"N139FW","t":"A139","f":"00","desc":""},"D36":{"r":"N139G","t":"T18","f":"00","desc":""},"D38":{"r":"N139GB","t":"DRON","f":"00","desc":""},"D3D":{"r":"N139GG","t":"P28B","f":"00","desc":"Piper PA-28 236 Dakota"},"D4F":{"r":"N139H","t":"A139","f":"00","desc":"2007 AGUSTA SPA AW139"},"D50":{"r":"N139HA","t":"UH12","f":"00","desc":""},"D52":{"r":"N139HC","t":"A139","f":"00","desc":"2014 AGUSTAWESTLAND SPA AW139"},"D54":{"r":"N139HE","t":"HDJT","f":"00","desc":""},"D55":{"r":"N139HF","t":"A139","f":"00","desc":"AB139"},"D5C":{"r":"N139HN","t":"EC30","f":"00","desc":"Eurocopter EC130 B4"},"D5D":{"r":"N139HP","t":"GA8","f":"01","desc":"GippsAero GA-8 Airvan TC 320"},"D68":{"r":"N139J","t":"SR20","f":"00","desc":"Cirrus Design SR20"},"D6A":{"r":"N139JB","t":"BE10","f":"00","desc":"Beech King Air B100"},"D6C":{"r":"N139JD","t":"MT","f":"00","desc":"AutoGyro Europe MTO Sport"},"D70":{"r":"N139JH","t":"AT3T","f":"00","desc":""},"D72":{"r":"N139JK","t":"L39","f":"00","desc":"Aero Vodochody L-39 C"},"D73":{"r":"N139JL","t":"RV8","f":"00","desc":""},"D74":{"r":"N139JM","t":"SR22","f":"00","desc":"2007 CIRRUS DESIGN CORP SR22"},"D76":{"r":"N139JP","t":"A139","f":"00","desc":"2005 AGUSTA SPA AB139"},"D87":{"r":"N139KF","t":"FOX","f":"00","desc":""},"D9D":{"r":"N139LC","t":"S22T","f":"00","desc":""},"D9F":{"r":"N139LE","t":"L39","f":"00","desc":"Aero Vodochody L-39 ZO"},"DA0":{"r":"N139LF","t":"PA46","f":"00","desc":"2011 PIPER AIRCRAFT INC PA 46-350P"},"DA3":{"r":"N139LJ","t":"CL60","f":"00","desc":"Bombardier Challenger 601 3A"},"DA5":{"r":"N139LL","t":"L39","f":"00","desc":""},"DAA":{"r":"N139LR","t":"LJ31","f":"00","desc":""},"DAB":{"r":"N139LS","t":"L39","f":"00","desc":"1974 AERO VODOCHODY L39C"},"DAF":{"r":"N139LW","t":"L39","f":"00","desc":""},"DB2":{"r":"N139LZ","t":"L39","f":"00","desc":"Aero Vodochody L-39 C"},"DB3":{"r":"N139M","t":"HUSK","f":"00","desc":"2015 AVIAT AIRCRAFT INC A-1C-180"},"DB4":{"r":"N139MA","t":"C172","f":"00","desc":"Cessna 172R Skyhawk"},"DB5":{"r":"N139MB","t":"CL60","f":"00","desc":""},"DB7":{"r":"N139MD","t":"L39","f":"00","desc":"1996 AERO VODOCHODY L39CT"},"DB8":{"r":"N139ME","t":"C172","f":"00","desc":"2000 CESSNA 172S"},"DB9":{"r":"N139MF","t":"L39","f":"00","desc":""},"DBB":{"r":"N139MH","t":"EC35","f":"00","desc":"Eurocopter EC135 T2"},"DBE":{"r":"N139ML","t":"ULAC","f":"00","desc":""},"DBF":{"r":"N139MM","t":"L39","f":"00","desc":""},"DC0":{"r":"N139MN","t":"DRON","f":"00","desc":""},"DC4":{"r":"N139MS","t":"L39","f":"01","desc":"1980 AERO VODOCHODY L39C"},"DCA":{"r":"N139MY","t":"C650","f":"00","desc":"1985 CESSNA 650"},"DCC":{"r":"N139N","t":"ULAC","f":"00","desc":""},"DE5":{"r":"N139P","t":"GLID","f":"00","desc":"1981 SCHEMPP-HIRTH VENTUS-B"},"DE8":{"r":"N139PC","t":"CH7B","f":"00","desc":""},"DE9":{"r":"N139PD","t":"B407","f":"00","desc":""},"DEE":{"r":"N139PJ","t":"L39","f":"00","desc":"AERO VODOCHODY L-39"},"DF0":{"r":"N139PL","t":"LJ31","f":"00","desc":""},"DF1":{"r":"N139PM","t":"L39","f":"00","desc":"1984 AERO VODOCHODY L39C"},"DF5":{"r":"N139PR","t":"A139","f":"00","desc":"AgustaWestland AW.139"},"DF6":{"r":"N139PS","t":"DA40","f":"00","desc":"2005 DIAMOND AIRCRAFT IND INC DA 40"},"DF7":{"r":"N139PT","t":"BE55","f":"00","desc":""},"DFE":{"r":"N139Q","t":"BE55","f":"00","desc":"Beech Baron B55"},"E17":{"r":"N139R","t":"BE35","f":"00","desc":"Beech Bonanza V35B"},"E18":{"r":"N139RA","t":"C182","f":"00","desc":"1999 CESSNA 182S"},"E1A":{"r":"N139RC","t":"PA18","f":"00","desc":""},"E1B":{"r":"N139RD","t":"B06","f":"00","desc":""},"E1E":{"r":"N139RG","t":"L39","f":"00","desc":"1981 AERO VODOCHODY L-39"},"E1F":{"r":"N139RH","t":"L39","f":"00","desc":""},"E21":{"r":"N139RK","t":"RV9","f":"00","desc":"Vans RV-9 A"},"E22":{"r":"N139RL","t":"P39","f":"00","desc":""},"E23":{"r":"N139RM","t":"L39","f":"00","desc":""},"E24":{"r":"N139RN","t":"C55B","f":"00","desc":"1999 CESSNA 550"},"E27":{"r":"N139RR","t":"BE20","f":"00","desc":"Beech King Air B200"},"E28":{"r":"N139RS","t":"L39","f":"00","desc":"1984 AERO VODOCHODY L-39"},"E2B":{"r":"N139RV","t":"RV9","f":"00","desc":"Hiatt Bradley J Rv-9A"},"E31":{"r":"N139SA","t":"C206","f":"00","desc":"2003 CESSNA 206H"},"E32":{"r":"N139SB","t":"ULAC","f":"00","desc":""},"E33":{"r":"N139SC","t":"BE9L","f":"00","desc":"1979 BEECH C90"},"E35":{"r":"N139SE","t":"PARA","f":"00","desc":""},"E36":{"r":"N139SF","t":"F8L","f":"00","desc":""},"E38":{"r":"N139SH","t":"L39","f":"00","desc":""},"E3D":{"r":"N139SN","t":"P28A","f":"00","desc":"Piper PA-28 180 Cherokee C"},"E40":{"r":"N139SR","t":"L39","f":"00","desc":""},"E42":{"r":"N139ST","t":"ULAC","f":"00","desc":""},"E45":{"r":"N139SW","t":"ULAC","f":"00","desc":""},"E47":{"r":"N139SY","t":"E170","f":"00","desc":"2015 EMBRAER S A ERJ170-200LR"},"E49":{"r":"N139T","t":"ZZZZ","f":"00","desc":""},"E4A":{"r":"N139TA","t":"BE35","f":"00","desc":""},"E4B":{"r":"N139TB","t":"L39","f":"00","desc":""},"E4D":{"r":"N139TD","t":"L39","f":"00","desc":""},"E4F":{"r":"N139TF","t":"RV8","f":"00","desc":""},"E52":{"r":"N139TJ","t":"EC35","f":"00","desc":"EUROCOPTER DEUTSCHLAND GMBH EC 135 P2"},"E54":{"r":"N139TL","t":"DRON","f":"00","desc":""},"E55":{"r":"N139TM","t":"ULAC","f":"00","desc":""},"E57":{"r":"N139TP","t":"A139","f":"00","desc":"AGUSTAWESTLAND PHILADELPHIA AW139"},"E59":{"r":"N139TR","t":"GLID","f":"00","desc":""},"E5A":{"r":"N139TS","t":"L39","f":"00","desc":""},"E5C":{"r":"N139TU","t":"P208","f":"00","desc":""},"E5E":{"r":"N139TW","t":"C172","f":"00","desc":"2002 CESSNA 172S"},"E5F":{"r":"N139TX","t":"RV6","f":"00","desc":""},"E61":{"r":"N139TZ","t":"A139","f":"00","desc":"2009 AGUSTA SPA AW139"},"E66":{"r":"N139UD","t":"C172","f":"00","desc":"2014 CESSNA 172S"},"E6A":{"r":"N139UH","t":"DRON","f":"00","desc":""},"E6C":{"r":"N139UK","t":"L39","f":"00","desc":""},"E70":{"r":"N139UP","t":"A306","f":"00","desc":"2001 AIRBUS INDUSTRIE A300F4-622R"},"E73":{"r":"N139US","t":"L39","f":"00","desc":""},"E87":{"r":"N139VM","t":"L39","f":"00","desc":""},"E8C":{"r":"N139VS","t":"L39","f":"00","desc":"1981 AERO VODOCHODY L-39"},"E9A":{"r":"N139WF","t":"BE9L","f":"00","desc":""},"E9B":{"r":"N139WG","t":"A119","f":"00","desc":""},"EA5":{"r":"N139WS","t":"L39","f":"00","desc":""},"EA6":{"r":"N139WT","t":"M20T","f":"00","desc":"2000 MOONEY M20M"},"EAD":{"r":"N139X","t":"SONX","f":"00","desc":""},"EB8":{"r":"N139XL","t":"C56X","f":"00","desc":""},"EC3":{"r":"N139XX","t":"","f":"00","desc":"1991 AERO VODOCHODY L39C"},"ED4":{"r":"N139YP","t":"P28R","f":"00","desc":"Piper PA-28R 201T Turbo Arrow III"},"EE0":{"r":"N139ZA","t":"L39","f":"00","desc":""},"EF5":{"r":"N139ZX","t":"DRIF","f":"00","desc":""},"EF9":{"r":"N1390A","t":"L39","f":"00","desc":"1992 AERO VODOCHODY L-139"},"EFA":{"r":"N1390B","t":"L8","f":"00","desc":""},"EFD":{"r":"N1390E","t":"CH7A","f":"00","desc":""},"F03":{"r":"N1390L","t":"C337","f":"00","desc":"Cessna 337H Super Skymaster"},"F05":{"r":"N1390N","t":"ST75","f":"00","desc":"Stearman Kaydet"},"F07":{"r":"N1390Q","t":"C150","f":"00","desc":""},"F08":{"r":"N1390R","t":"AA5","f":"00","desc":"Grumman American AA5"},"F0A":{"r":"N1390T","t":"PA34","f":"00","desc":"Piper PA-34 200 Seneca"},"F0E":{"r":"N1390X","t":"B47G","f":"00","desc":""},"F0F":{"r":"N1390Y","t":"C172","f":"00","desc":""},"F10":{"r":"N1390Z","t":"BE35","f":"00","desc":""},"F12":{"r":"N13901","t":"PA27","f":"00","desc":"Piper PA-23 Aztec 250D"},"F13":{"r":"N13902","t":"C172","f":"00","desc":""},"F14":{"r":"N13903","t":"E145","f":"00","desc":"Embraer ERJ145LR"},"F15":{"r":"N13904","t":"PA18","f":"00","desc":"Piper PA-18 150 Super Cub"},"F16":{"r":"N13905","t":"C172","f":"00","desc":"Cessna 172M Skyhawk"},"F17":{"r":"N13906","t":"TVLB","f":"00","desc":""},"F18":{"r":"N13907","t":"TVLB","f":"00","desc":""},"F19":{"r":"N13908","t":"E145","f":"00","desc":"2001 EMBRAER EMB-145LR"},"F1C":{"r":"N1391A","t":"C182","f":"00","desc":"2007 CESSNA T182T"},"F1E":{"r":"N1391C","t":"PA22","f":"00","desc":""},"F23":{"r":"N1391H","t":"AR15","f":"00","desc":""},"F28":{"r":"N1391N","t":"PA18","f":"00","desc":""},"F2A":{"r":"N1391Q","t":"C150","f":"00","desc":""},"F2B":{"r":"N1391R","t":"AA5","f":"00","desc":""},"F2C":{"r":"N1391S","t":"C182","f":"00","desc":""},"F2D":{"r":"N1391T","t":"PA32","f":"00","desc":"1972 PIPER PA-32-300"},"F2E":{"r":"N1391U","t":"C172","f":"00","desc":"Cessna 172M Skyhawk"},"F30":{"r":"N1391W","t":"LGEZ","f":"00","desc":""},"F34":{"r":"N13910","t":"PA18","f":"00","desc":"PA-18"},"F35":{"r":"N13911","t":"PA18","f":"00","desc":"1971 PIPER PA-18-150"},"F37":{"r":"N13913","t":"E145","f":"00","desc":"2001 EMBRAER EMB-145LR"},"F3A":{"r":"N13916","t":"PA27","f":"00","desc":"1970 PIPER PA-23-250"},"F3B":{"r":"N13917","t":"WACO","f":"00","desc":""},"F3C":{"r":"N13918","t":"WACO","f":"00","desc":"1929 WACO ATO"},"F3F":{"r":"N1392A","t":"PA18","f":"00","desc":"1951 PIPER PA-18"},"F40":{"r":"N1392B","t":"L8","f":"00","desc":""},"F42":{"r":"N1392D","t":"C170","f":"00","desc":""},"F43":{"r":"N1392E","t":"CH7A","f":"00","desc":""},"F4D":{"r":"N1392Q","t":"C150","f":"00","desc":""},"F4F":{"r":"N1392S","t":"C182","f":"00","desc":"1976 CESSNA 182P"},"F53":{"r":"N1392W","t":"M20P","f":"00","desc":""},"F55":{"r":"N1392Y","t":"C172","f":"00","desc":""},"F56":{"r":"N1392Z","t":"BE35","f":"00","desc":"1961 BEECH N35"},"F57":{"r":"N13920","t":"ZZZZ","f":"00","desc":""},"F59":{"r":"N13922","t":"EXEC","f":"00","desc":""},"F5A":{"r":"N13923","t":"C172","f":"00","desc":"1974 CESSNA 172M"},"F5B":{"r":"N13924","t":"PA27","f":"00","desc":"URIEL BRISTOL CASSUTT IIIM"},"F5C":{"r":"N13925","t":"PA18","f":"00","desc":"1971 PIPER PA-18-150"},"F5E":{"r":"N13927","t":"PA18","f":"00","desc":""},"F66":{"r":"N1393E","t":"C172","f":"00","desc":"Cessna 172N Skyhawk"},"F67":{"r":"N1393F","t":"C185","f":"00","desc":"1975 CESSNA A185F"},"F6A":{"r":"N1393J","t":"AC11","f":"00","desc":""},"F6F":{"r":"N1393P","t":"PA23","f":"00","desc":""},"F70":{"r":"N1393Q","t":"C150","f":"00","desc":"Cessna 150L"},"F74":{"r":"N1393U","t":"C172","f":"00","desc":"Cessna 172M Skyhawk"},"F75":{"r":"N1393V","t":"EAGL","f":"00","desc":""},"F76":{"r":"N1393W","t":"COL3","f":"00","desc":"2006 COLUMBIA AIRCRAFT MFG LC42-550FG"},"F78":{"r":"N1393Y","t":"C172","f":"00","desc":""},"F79":{"r":"N1393Z","t":"BE35","f":"00","desc":""},"F7B":{"r":"N13931","t":"PA18","f":"00","desc":""},"F7E":{"r":"N13934","t":"ZZZZ","f":"00","desc":""},"F81":{"r":"N13937","t":"PA18","f":"00","desc":""},"F82":{"r":"N13938","t":"C172","f":"00","desc":"CESSNA 172M"},"F83":{"r":"N13939","t":"C177","f":"00","desc":"1976 CESSNA 177B"},"F84":{"r":"N1394","t":"C172","f":"00","desc":""},"F89":{"r":"N1394E","t":"CH7A","f":"00","desc":""},"F8A":{"r":"N1394F","t":"C172","f":"00","desc":""},"F8B":{"r":"N1394G","t":"KR2","f":"00","desc":""},"F8D":{"r":"N1394J","t":"AC11","f":"00","desc":""},"F8E":{"r":"N1394K","t":"L8","f":"00","desc":""},"F90":{"r":"N1394M","t":"C182","f":"00","desc":"182"},"F93":{"r":"N1394Q","t":"C150","f":"00","desc":""},"F94":{"r":"N1394R","t":"PA18","f":"00","desc":""},"F95":{"r":"N1394S","t":"C182","f":"00","desc":"1976 CESSNA 182P"},"F99":{"r":"N1394W","t":"M20P","f":"00","desc":""},"F9A":{"r":"N1394X","t":"B47G","f":"00","desc":""},"F9B":{"r":"N1394Y","t":"PA18","f":"00","desc":""},"F9E":{"r":"N13941","t":"C172","f":"00","desc":"Cessna 172M Skyhawk"},"F9F":{"r":"N13942","t":"C172","f":"00","desc":"Cessna 172M Skyhawk"},"FA0":{"r":"N13943","t":"C172","f":"00","desc":""},"FA1":{"r":"N13944","t":"C172","f":"00","desc":"Cessna 172M Skyhawk"},"FA3":{"r":"N13946","t":"C172","f":"00","desc":""},"FA5":{"r":"N13948","t":"ULAC","f":"00","desc":""},"FA6":{"r":"N13949","t":"E145","f":"00","desc":"Embraer ERJ-145 LR"},"FAC":{"r":"N1395E","t":"C172","f":"00","desc":"1978 CESSNA 172N"},"FAD":{"r":"N1395F","t":"BOLT","f":"00","desc":""},"FB0":{"r":"N1395J","t":"AC11","f":"00","desc":""},"FB7":{"r":"N1395R","t":"AA5","f":"00","desc":"1975 GRUMMAN AMERICAN AVN. CORP. AA-5"},"FB8":{"r":"N1395S","t":"C182","f":"00","desc":""},"FB9":{"r":"N1395T","t":"P28R","f":"00","desc":"1972 PIPER PA-28R-200"},"FBA":{"r":"N1395U","t":"C172","f":"00","desc":"Cessna 172M Skyhawk"},"FBB":{"r":"N1395V","t":"COL4","f":"00","desc":"2006 COLUMBIA AIRCRAFT MFG LC41-550FG"},"FBC":{"r":"N1395W","t":"M20P","f":"00","desc":"Mooney M.20C Mark 21"},"FBE":{"r":"N1395Y","t":"C172","f":"00","desc":"1961 CESSNA 172C"},"FC0":{"r":"N13950","t":"PA27","f":"00","desc":"Piper PA-23 Aztec 250D"},"FC1":{"r":"N13951","t":"PA18","f":"00","desc":""},"FC4":{"r":"N13954","t":"B789","f":"00","desc":"2015 BOEING 787-9"},"FC7":{"r":"N13957","t":"ULAC","f":"00","desc":""},"FCB":{"r":"N1396A","t":"BE35","f":"00","desc":""},"FCD":{"r":"N1396C","t":"SCOR","f":"00","desc":""},"FCE":{"r":"N1396D","t":"C170","f":"00","desc":""},"FD2":{"r":"N1396H","t":"AR15","f":"00","desc":""},"FD4":{"r":"N1396K","t":"L8","f":"00","desc":""},"FDA":{"r":"N1396R","t":"AA5","f":"00","desc":""},"FDF":{"r":"N1396W","t":"M20P","f":"00","desc":"Mooney M.20C Mark 21"},"FE0":{"r":"N1396X","t":"B47G","f":"00","desc":""},"FE2":{"r":"N1396Z","t":"BE33","f":"00","desc":"1961 BEECH 35-B33"},"FE3":{"r":"N13960","t":"PA18","f":"00","desc":""},"FE7":{"r":"N13964","t":"E145","f":"00","desc":"Embraer ERJ-145 LR"},"FE8":{"r":"N13965","t":"E145","f":"00","desc":"1999 EMBRAER EMB-145LR"},"FE9":{"r":"N13966","t":"PA27","f":"00","desc":"1970 PIPER PA-23-250"},"FEA":{"r":"N13967","t":"PA27","f":"00","desc":"1970 PIPER PA-23-250"},"FEC":{"r":"N13969","t":"E145","f":"00","desc":"Embraer ERJ-145 LR"},"FF0":{"r":"N1397C","t":"PA22","f":"00","desc":""},"FF2":{"r":"N1397E","t":"CH7A","f":"00","desc":""},"FF5":{"r":"N1397H","t":"PA34","f":"00","desc":"Piper PA-34 200T Seneca II"},"FF9":{"r":"N1397M","t":"C210","f":"00","desc":""},"FFE":{"r":"N1397S","t":"C182","f":"00","desc":"1976 CESSNA 182P"}}